{
"meta":{"test_sets":[],"test_metrics":[],"learn_metrics":[{"best_value":"Min","name":"Logloss"}],"launch_mode":"Train","parameters":"","iteration_count":1000,"learn_sets":["learn"],"name":"experiment"},
"iterations":[
{"learn":[0.5872866041],"iteration":0,"passed_time":0.1864239896,"remaining_time":186.2375656},
{"learn":[0.4995516902],"iteration":1,"passed_time":0.1987841421,"remaining_time":99.19328688},
{"learn":[0.4458502428],"iteration":2,"passed_time":0.2120453963,"remaining_time":70.46975338},
{"learn":[0.4019638621],"iteration":3,"passed_time":0.2253927985,"remaining_time":56.12280681},
{"learn":[0.3681923126],"iteration":4,"passed_time":0.2384256304,"remaining_time":47.44670045},
{"learn":[0.340683287],"iteration":5,"passed_time":0.2515843985,"remaining_time":41.67914869},
{"learn":[0.3254665861],"iteration":6,"passed_time":0.2644379249,"remaining_time":37.51240848},
{"learn":[0.3087560626],"iteration":7,"passed_time":0.2763672604,"remaining_time":34.26954029},
{"learn":[0.2934287592],"iteration":8,"passed_time":0.2899742675,"remaining_time":31.92938879},
{"learn":[0.2827675473],"iteration":9,"passed_time":0.3011224396,"remaining_time":29.81112152},
{"learn":[0.2763441762],"iteration":10,"passed_time":0.3134998637,"remaining_time":28.18648774},
{"learn":[0.2689537225],"iteration":11,"passed_time":0.3254740031,"remaining_time":26.79735959},
{"learn":[0.2625766605],"iteration":12,"passed_time":0.3366902485,"remaining_time":25.56255963},
{"learn":[0.2574017784],"iteration":13,"passed_time":0.3490287062,"remaining_time":24.58159316},
{"learn":[0.252831581],"iteration":14,"passed_time":0.361646067,"remaining_time":23.74809173},
{"learn":[0.2502004682],"iteration":15,"passed_time":0.3737266243,"remaining_time":22.98418739},
{"learn":[0.2472268416],"iteration":16,"passed_time":0.3843927062,"remaining_time":22.22694295},
{"learn":[0.2448275656],"iteration":17,"passed_time":0.3958746553,"remaining_time":21.59716175},
{"learn":[0.2435681971],"iteration":18,"passed_time":0.4079458346,"remaining_time":21.06288757},
{"learn":[0.2419975482],"iteration":19,"passed_time":0.4194842223,"remaining_time":20.55472689},
{"learn":[0.2410104122],"iteration":20,"passed_time":0.4314182519,"remaining_time":20.11230803},
{"learn":[0.2394196498],"iteration":21,"passed_time":0.4432687419,"remaining_time":19.70531044},
{"learn":[0.2379917312],"iteration":22,"passed_time":0.4555704699,"remaining_time":19.35184126},
{"learn":[0.2372168638],"iteration":23,"passed_time":0.4671312645,"remaining_time":18.99667142},
{"learn":[0.2360539623],"iteration":24,"passed_time":0.4781216452,"remaining_time":18.64674416},
{"learn":[0.2353284413],"iteration":25,"passed_time":0.4903919293,"remaining_time":18.37083612},
{"learn":[0.2348208642],"iteration":26,"passed_time":0.5028536151,"remaining_time":18.12135435},
{"learn":[0.2341772508],"iteration":27,"passed_time":0.5151323443,"remaining_time":17.88245138},
{"learn":[0.2335064736],"iteration":28,"passed_time":0.5271583487,"remaining_time":17.65071574},
{"learn":[0.2329812946],"iteration":29,"passed_time":0.5397357401,"remaining_time":17.4514556},
{"learn":[0.2325485219],"iteration":30,"passed_time":0.5523771227,"remaining_time":17.26623974},
{"learn":[0.2322608804],"iteration":31,"passed_time":0.5649490278,"remaining_time":17.08970809},
{"learn":[0.2317975846],"iteration":32,"passed_time":0.5759786256,"remaining_time":16.87791912},
{"learn":[0.2313607915],"iteration":33,"passed_time":0.5879363865,"remaining_time":16.70431028},
{"learn":[0.2310099141],"iteration":34,"passed_time":0.6002205621,"remaining_time":16.54893835},
{"learn":[0.2304388742],"iteration":35,"passed_time":0.6113290355,"remaining_time":16.37003306},
{"learn":[0.2301352861],"iteration":36,"passed_time":0.6223060764,"remaining_time":16.19677707},
{"learn":[0.2298364341],"iteration":37,"passed_time":0.6341488634,"remaining_time":16.05397912},
{"learn":[0.2295065302],"iteration":38,"passed_time":0.6458936577,"remaining_time":15.91548218},
{"learn":[0.2290854329],"iteration":39,"passed_time":0.6555707252,"remaining_time":15.73369741},
{"learn":[0.2286716768],"iteration":40,"passed_time":0.6693079112,"remaining_time":15.65527529},
{"learn":[0.2284950622],"iteration":41,"passed_time":0.6819044298,"remaining_time":15.55391533},
{"learn":[0.2282860928],"iteration":42,"passed_time":0.6940024894,"remaining_time":15.44559029},
{"learn":[0.2280041988],"iteration":43,"passed_time":0.7046063956,"remaining_time":15.30917532},
{"learn":[0.2278533897],"iteration":44,"passed_time":0.7163017522,"remaining_time":15.20151496},
{"learn":[0.2275715778],"iteration":45,"passed_time":0.7294302905,"remaining_time":15.12774994},
{"learn":[0.2273985563],"iteration":46,"passed_time":0.7439275771,"remaining_time":15.08431874},
{"learn":[0.2272585609],"iteration":47,"passed_time":0.7605119784,"remaining_time":15.08348757},
{"learn":[0.2271056686],"iteration":48,"passed_time":0.7749109111,"remaining_time":15.03959748},
{"learn":[0.2270166575],"iteration":49,"passed_time":0.7897414136,"remaining_time":15.00508686},
{"learn":[0.2268147896],"iteration":50,"passed_time":0.8009348308,"remaining_time":14.90366969},
{"learn":[0.2267373051],"iteration":51,"passed_time":0.8130514262,"remaining_time":14.82255292},
{"learn":[0.2264377596],"iteration":52,"passed_time":0.8250004606,"remaining_time":14.74104597},
{"learn":[0.2262624126],"iteration":53,"passed_time":0.8368749223,"remaining_time":14.66080882},
{"learn":[0.2260403794],"iteration":54,"passed_time":0.8473964123,"remaining_time":14.55981108},
{"learn":[0.2258190153],"iteration":55,"passed_time":0.8599294713,"remaining_time":14.49595394},
{"learn":[0.2256632123],"iteration":56,"passed_time":0.8721105087,"remaining_time":14.42807385},
{"learn":[0.2255194955],"iteration":57,"passed_time":0.8826088596,"remaining_time":14.33478527},
{"learn":[0.2253077227],"iteration":58,"passed_time":0.8937395294,"remaining_time":14.25438809},
{"learn":[0.2251946785],"iteration":59,"passed_time":0.9059322116,"remaining_time":14.19293798},
{"learn":[0.2250196167],"iteration":60,"passed_time":0.9175599161,"remaining_time":14.12440592},
{"learn":[0.2248379373],"iteration":61,"passed_time":0.9278903554,"remaining_time":14.03808312},
{"learn":[0.2246694318],"iteration":62,"passed_time":0.9402395853,"remaining_time":13.98419828},
{"learn":[0.2245076062],"iteration":63,"passed_time":0.9525083247,"remaining_time":13.93043425},
{"learn":[0.2243870051],"iteration":64,"passed_time":0.9638781088,"remaining_time":13.86501587},
{"learn":[0.2242923531],"iteration":65,"passed_time":0.9749556002,"remaining_time":13.79709895},
{"learn":[0.2241857554],"iteration":66,"passed_time":0.9873887708,"remaining_time":13.74975706},
{"learn":[0.22410544],"iteration":67,"passed_time":0.999604733,"remaining_time":13.70046487},
{"learn":[0.2240075511],"iteration":68,"passed_time":1.009772537,"remaining_time":13.62461205},
{"learn":[0.2238959478],"iteration":69,"passed_time":1.02227375,"remaining_time":13.58163697},
{"learn":[0.2238371904],"iteration":70,"passed_time":1.034019317,"remaining_time":13.52963303},
{"learn":[0.2237516066],"iteration":71,"passed_time":1.046427312,"remaining_time":13.48728536},
{"learn":[0.2236165277],"iteration":72,"passed_time":1.057615896,"remaining_time":13.43027309},
{"learn":[0.223544977],"iteration":73,"passed_time":1.069861125,"remaining_time":13.38772164},
{"learn":[0.2233840467],"iteration":74,"passed_time":1.081526682,"remaining_time":13.33882908},
{"learn":[0.2231576022],"iteration":75,"passed_time":1.093109864,"remaining_time":13.28991466},
{"learn":[0.2230335672],"iteration":76,"passed_time":1.104128359,"remaining_time":13.23520097},
{"learn":[0.2229021302],"iteration":77,"passed_time":1.116465181,"remaining_time":13.19719099},
{"learn":[0.222783342],"iteration":78,"passed_time":1.129260213,"remaining_time":13.16517287},
{"learn":[0.2226351571],"iteration":79,"passed_time":1.139250878,"remaining_time":13.10138509},
{"learn":[0.222468382],"iteration":80,"passed_time":1.15063687,"remaining_time":13.05475659},
{"learn":[0.2223229381],"iteration":81,"passed_time":1.163184372,"remaining_time":13.0219909},
{"learn":[0.2222342862],"iteration":82,"passed_time":1.175458327,"remaining_time":12.9866902},
{"learn":[0.2220995131],"iteration":83,"passed_time":1.185916338,"remaining_time":12.9321353},
{"learn":[0.2219544195],"iteration":84,"passed_time":1.198419417,"remaining_time":12.90063255},
{"learn":[0.2217444948],"iteration":85,"passed_time":1.210405181,"remaining_time":12.86407367},
{"learn":[0.2215490917],"iteration":86,"passed_time":1.223002683,"remaining_time":12.83449942},
{"learn":[0.221462076],"iteration":87,"passed_time":1.23421612,"remaining_time":12.79096706},
{"learn":[0.2213318053],"iteration":88,"passed_time":1.245911787,"remaining_time":12.75309706},
{"learn":[0.221221775],"iteration":89,"passed_time":1.258453071,"remaining_time":12.72435883},
{"learn":[0.2211510345],"iteration":90,"passed_time":1.270137144,"remaining_time":12.68741389},
{"learn":[0.2210720357],"iteration":91,"passed_time":1.281540207,"remaining_time":12.64824466},
{"learn":[0.220991333],"iteration":92,"passed_time":1.294384847,"remaining_time":12.62373179},
{"learn":[0.2209407386],"iteration":93,"passed_time":1.306824688,"remaining_time":12.59556561},
{"learn":[0.2208751421],"iteration":94,"passed_time":1.319675787,"remaining_time":12.57164828},
{"learn":[0.2206861476],"iteration":95,"passed_time":1.33126273,"remaining_time":12.53605737},
{"learn":[0.2206128336],"iteration":96,"passed_time":1.343505852,"remaining_time":12.50706995},
{"learn":[0.2204665431],"iteration":97,"passed_time":1.356091117,"remaining_time":12.48157335},
{"learn":[0.2203417259],"iteration":98,"passed_time":1.367532706,"remaining_time":12.44592897},
{"learn":[0.2202970632],"iteration":99,"passed_time":1.377783307,"remaining_time":12.40004976},
{"learn":[0.2201571673],"iteration":100,"passed_time":1.389981676,"remaining_time":12.37221314},
{"learn":[0.2200536392],"iteration":101,"passed_time":1.402015443,"remaining_time":12.343234},
{"learn":[0.2199841549],"iteration":102,"passed_time":1.412227499,"remaining_time":12.29871909},
{"learn":[0.2198442952],"iteration":103,"passed_time":1.424227967,"remaining_time":12.27027172},
{"learn":[0.2197497329],"iteration":104,"passed_time":1.436368283,"remaining_time":12.24332965},
{"learn":[0.2196442576],"iteration":105,"passed_time":1.449239081,"remaining_time":12.22282772},
{"learn":[0.2194342471],"iteration":106,"passed_time":1.459921411,"remaining_time":12.18420393},
{"learn":[0.2192446712],"iteration":107,"passed_time":1.472115668,"remaining_time":12.15858496},
{"learn":[0.2190753481],"iteration":108,"passed_time":1.484019758,"remaining_time":12.13084041},
{"learn":[0.2189261974],"iteration":109,"passed_time":1.495875263,"remaining_time":12.10299077},
{"learn":[0.2187548736],"iteration":110,"passed_time":1.506875945,"remaining_time":12.06858302},
{"learn":[0.2186080015],"iteration":111,"passed_time":1.527049117,"remaining_time":12.107318},
{"learn":[0.2185275306],"iteration":112,"passed_time":1.538732989,"remaining_time":12.07837311},
{"learn":[0.2184564027],"iteration":113,"passed_time":1.552081725,"remaining_time":12.06267025},
{"learn":[0.2183703737],"iteration":114,"passed_time":1.564277205,"remaining_time":12.03813327},
{"learn":[0.2182520217],"iteration":115,"passed_time":1.57651103,"remaining_time":12.0141013},
{"learn":[0.21816661],"iteration":116,"passed_time":1.587813543,"remaining_time":11.98324238},
{"learn":[0.2179978548],"iteration":117,"passed_time":1.599814463,"remaining_time":11.95793522},
{"learn":[0.2178400633],"iteration":118,"passed_time":1.612224103,"remaining_time":11.9358776},
{"learn":[0.2177184195],"iteration":119,"passed_time":1.62371861,"remaining_time":11.9072698},
{"learn":[0.2176205783],"iteration":120,"passed_time":1.636085372,"remaining_time":11.88528134},
{"learn":[0.2175714097],"iteration":121,"passed_time":1.649833611,"remaining_time":11.87339271},
{"learn":[0.2174415108],"iteration":122,"passed_time":1.66254062,"remaining_time":11.85404978},
{"learn":[0.2173320586],"iteration":123,"passed_time":1.675491587,"remaining_time":11.83653734},
{"learn":[0.2171454813],"iteration":124,"passed_time":1.688105729,"remaining_time":11.8167401},
{"learn":[0.2170176172],"iteration":125,"passed_time":1.700075876,"remaining_time":11.79258981},
{"learn":[0.2168902848],"iteration":126,"passed_time":1.712966162,"remaining_time":11.77495638},
{"learn":[0.216809556],"iteration":127,"passed_time":1.726209292,"remaining_time":11.7598008},
{"learn":[0.2166574593],"iteration":128,"passed_time":1.739567065,"remaining_time":11.74544894},
{"learn":[0.2165429098],"iteration":129,"passed_time":1.749902289,"remaining_time":11.71088455},
{"learn":[0.2164597352],"iteration":130,"passed_time":1.762763869,"remaining_time":11.69344887},
{"learn":[0.2162739632],"iteration":131,"passed_time":1.775520406,"remaining_time":11.67539176},
{"learn":[0.2161095671],"iteration":132,"passed_time":1.788580569,"remaining_time":11.65939364},
{"learn":[0.2159834301],"iteration":133,"passed_time":1.801221952,"remaining_time":11.64073291},
{"learn":[0.2158464033],"iteration":134,"passed_time":1.813730227,"remaining_time":11.62130849},
{"learn":[0.2157517322],"iteration":135,"passed_time":1.82790161,"remaining_time":11.6125514},
{"learn":[0.2155725828],"iteration":136,"passed_time":1.841620581,"remaining_time":11.60086541},
{"learn":[0.2154431907],"iteration":137,"passed_time":1.857800414,"remaining_time":11.60452143},
{"learn":[0.2153640582],"iteration":138,"passed_time":1.87352605,"remaining_time":11.60507863},
{"learn":[0.2151609768],"iteration":139,"passed_time":1.889532986,"remaining_time":11.6071312},
{"learn":[0.2148896511],"iteration":140,"passed_time":1.903541713,"remaining_time":11.59675413},
{"learn":[0.2147395338],"iteration":141,"passed_time":1.916559551,"remaining_time":11.58033869},
{"learn":[0.2146963603],"iteration":142,"passed_time":1.928304024,"remaining_time":11.5563395},
{"learn":[0.2144677568],"iteration":143,"passed_time":1.941014342,"remaining_time":11.53825192},
{"learn":[0.2143405191],"iteration":144,"passed_time":1.954142138,"remaining_time":11.52270019},
{"learn":[0.2142156999],"iteration":145,"passed_time":1.966277459,"remaining_time":11.50137637},
{"learn":[0.2140580964],"iteration":146,"passed_time":1.97920954,"remaining_time":11.48480094},
{"learn":[0.2139133885],"iteration":147,"passed_time":1.991019098,"remaining_time":11.46181264},
{"learn":[0.213783067],"iteration":148,"passed_time":2.004993492,"remaining_time":11.45133867},
{"learn":[0.2136643125],"iteration":149,"passed_time":2.018447833,"remaining_time":11.43787106},
{"learn":[0.2135939574],"iteration":150,"passed_time":2.032689125,"remaining_time":11.42882826},
{"learn":[0.2134687242],"iteration":151,"passed_time":2.046454947,"remaining_time":11.41706444},
{"learn":[0.2133218567],"iteration":152,"passed_time":2.057907277,"remaining_time":11.39246709},
{"learn":[0.213179817],"iteration":153,"passed_time":2.069557198,"remaining_time":11.36912591},
{"learn":[0.2131160524],"iteration":154,"passed_time":2.0822352,"remaining_time":11.35154029},
{"learn":[0.2130323551],"iteration":155,"passed_time":2.096043328,"remaining_time":11.34013185},
{"learn":[0.2128948288],"iteration":156,"passed_time":2.108603528,"remaining_time":11.32199219},
{"learn":[0.212816228],"iteration":157,"passed_time":2.119571362,"remaining_time":11.29543726},
{"learn":[0.2126456032],"iteration":158,"passed_time":2.132999585,"remaining_time":11.28209214},
{"learn":[0.2124868726],"iteration":159,"passed_time":2.149745468,"remaining_time":11.28616371},
{"learn":[0.2123160908],"iteration":160,"passed_time":2.164832226,"remaining_time":11.28133067},
{"learn":[0.21215975],"iteration":161,"passed_time":2.177895248,"remaining_time":11.26590258},
{"learn":[0.2120932542],"iteration":162,"passed_time":2.191346179,"remaining_time":11.25249541},
{"learn":[0.2120007993],"iteration":163,"passed_time":2.203562622,"remaining_time":11.23279483},
{"learn":[0.2118476553],"iteration":164,"passed_time":2.215493181,"remaining_time":11.21173822},
{"learn":[0.2118011279],"iteration":165,"passed_time":2.227933433,"remaining_time":11.19335231},
{"learn":[0.2117721953],"iteration":166,"passed_time":2.240358901,"remaining_time":11.17496386},
{"learn":[0.2116550564],"iteration":167,"passed_time":2.253828257,"remaining_time":11.16181613},
{"learn":[0.2115193003],"iteration":168,"passed_time":2.26540208,"remaining_time":11.13934396},
{"learn":[0.2113795104],"iteration":169,"passed_time":2.278904044,"remaining_time":11.12641386},
{"learn":[0.2112328557],"iteration":170,"passed_time":2.291013738,"remaining_time":11.10672742},
{"learn":[0.2111226394],"iteration":171,"passed_time":2.30316941,"remaining_time":11.08735041},
{"learn":[0.2109547347],"iteration":172,"passed_time":2.314190161,"remaining_time":11.06263158},
{"learn":[0.2108152429],"iteration":173,"passed_time":2.326431418,"remaining_time":11.04386409},
{"learn":[0.2106623162],"iteration":174,"passed_time":2.339984354,"remaining_time":11.03135481},
{"learn":[0.2104421678],"iteration":175,"passed_time":2.351822187,"remaining_time":11.01080387},
{"learn":[0.2103276183],"iteration":176,"passed_time":2.362731004,"remaining_time":10.98603173},
{"learn":[0.2101954583],"iteration":177,"passed_time":2.374720489,"remaining_time":10.96640586},
{"learn":[0.2101085464],"iteration":178,"passed_time":2.387407468,"remaining_time":10.95006442},
{"learn":[0.210015573],"iteration":179,"passed_time":2.399422339,"remaining_time":10.93070177},
{"learn":[0.2099488307],"iteration":180,"passed_time":2.409773751,"remaining_time":10.90389338},
{"learn":[0.2098619134],"iteration":181,"passed_time":2.422994434,"remaining_time":10.8901618},
{"learn":[0.2097013285],"iteration":182,"passed_time":2.435480052,"remaining_time":10.87315411},
{"learn":[0.2094191576],"iteration":183,"passed_time":2.447813334,"remaining_time":10.85552},
{"learn":[0.2093282175],"iteration":184,"passed_time":2.458004337,"remaining_time":10.82850559},
{"learn":[0.2092091582],"iteration":185,"passed_time":2.469533898,"remaining_time":10.80753007},
{"learn":[0.2090556133],"iteration":186,"passed_time":2.481487065,"remaining_time":10.78849724},
{"learn":[0.2088822486],"iteration":187,"passed_time":2.491958706,"remaining_time":10.76314079},
{"learn":[0.208778252],"iteration":188,"passed_time":2.502717385,"remaining_time":10.73917354},
{"learn":[0.2086636601],"iteration":189,"passed_time":2.514956857,"remaining_time":10.72165818},
{"learn":[0.2085368963],"iteration":190,"passed_time":2.524922376,"remaining_time":10.6945665},
{"learn":[0.2083530677],"iteration":191,"passed_time":2.535295423,"remaining_time":10.66936824},
{"learn":[0.2082288902],"iteration":192,"passed_time":2.547665475,"remaining_time":10.65267377},
{"learn":[0.2081468538],"iteration":193,"passed_time":2.560449534,"remaining_time":10.63774394},
{"learn":[0.2080622914],"iteration":194,"passed_time":2.57285061,"remaining_time":10.62125508},
{"learn":[0.2079777835],"iteration":195,"passed_time":2.583840569,"remaining_time":10.59901948},
{"learn":[0.2079027573],"iteration":196,"passed_time":2.595190744,"remaining_time":10.57836633},
{"learn":[0.2077510922],"iteration":197,"passed_time":2.608520644,"remaining_time":10.56582604},
{"learn":[0.2076646646],"iteration":198,"passed_time":2.621979829,"remaining_time":10.55379821},
{"learn":[0.207648561],"iteration":199,"passed_time":2.637559991,"remaining_time":10.55023996},
{"learn":[0.2075041707],"iteration":200,"passed_time":2.650564959,"remaining_time":10.53632539},
{"learn":[0.2073777873],"iteration":201,"passed_time":2.666575306,"remaining_time":10.53429255},
{"learn":[0.2072741321],"iteration":202,"passed_time":2.683064202,"remaining_time":10.53400083},
{"learn":[0.2070941125],"iteration":203,"passed_time":2.698454577,"remaining_time":10.52926394},
{"learn":[0.2070073431],"iteration":204,"passed_time":2.71078488,"remaining_time":10.512556},
{"learn":[0.2069185188],"iteration":205,"passed_time":2.726477207,"remaining_time":10.50884904},
{"learn":[0.2067979812],"iteration":206,"passed_time":2.739977716,"remaining_time":10.49662961},
{"learn":[0.2066807734],"iteration":207,"passed_time":2.753623459,"remaining_time":10.48495086},
{"learn":[0.206615913],"iteration":208,"passed_time":2.766038856,"remaining_time":10.46859682},
{"learn":[0.2064862116],"iteration":209,"passed_time":2.77757239,"remaining_time":10.4489628},
{"learn":[0.2063917757],"iteration":210,"passed_time":2.789941429,"remaining_time":10.4325298},
{"learn":[0.2062868772],"iteration":211,"passed_time":2.801580096,"remaining_time":10.41342036},
{"learn":[0.2062324702],"iteration":212,"passed_time":2.813058866,"remaining_time":10.39379027},
{"learn":[0.2061464908],"iteration":213,"passed_time":2.825057929,"remaining_time":10.37614735},
{"learn":[0.2060272362],"iteration":214,"passed_time":2.837987513,"remaining_time":10.36195441},
{"learn":[0.2059919344],"iteration":215,"passed_time":2.850762384,"remaining_time":10.34721162},
{"learn":[0.2058855739],"iteration":216,"passed_time":2.861116384,"remaining_time":10.32375174},
{"learn":[0.205782582],"iteration":217,"passed_time":2.872451755,"remaining_time":10.30393244},
{"learn":[0.2056879727],"iteration":218,"passed_time":2.884659352,"remaining_time":10.28730116},
{"learn":[0.2055447523],"iteration":219,"passed_time":2.89671321,"remaining_time":10.27016502},
{"learn":[0.2054571982],"iteration":220,"passed_time":2.907794562,"remaining_time":10.24964689},
{"learn":[0.205363202],"iteration":221,"passed_time":2.919167997,"remaining_time":10.23023739},
{"learn":[0.2053014501],"iteration":222,"passed_time":2.931450447,"remaining_time":10.21406725},
{"learn":[0.2051811782],"iteration":223,"passed_time":2.943464717,"remaining_time":10.19700277},
{"learn":[0.2050673777],"iteration":224,"passed_time":2.954421858,"remaining_time":10.17634196},
{"learn":[0.2050075308],"iteration":225,"passed_time":2.966367784,"remaining_time":10.15915338},
{"learn":[0.2048655745],"iteration":226,"passed_time":2.97812321,"remaining_time":10.1413623},
{"learn":[0.2047215141],"iteration":227,"passed_time":2.989035006,"remaining_time":10.12076765},
{"learn":[0.2046196319],"iteration":228,"passed_time":3.001249232,"remaining_time":10.10464261},
{"learn":[0.2045523231],"iteration":229,"passed_time":3.013206952,"remaining_time":10.08769284},
{"learn":[0.2044358186],"iteration":230,"passed_time":3.025394078,"remaining_time":10.07154998},
{"learn":[0.2043365138],"iteration":231,"passed_time":3.037025434,"remaining_time":10.05360144},
{"learn":[0.2042137097],"iteration":232,"passed_time":3.050691417,"remaining_time":10.04240479},
{"learn":[0.2040822036],"iteration":233,"passed_time":3.062984288,"remaining_time":10.02669216},
{"learn":[0.2039332277],"iteration":234,"passed_time":3.074439086,"remaining_time":10.00828043},
{"learn":[0.2038140997],"iteration":235,"passed_time":3.087680091,"remaining_time":9.995710124},
{"learn":[0.2037100289],"iteration":236,"passed_time":3.098412862,"remaining_time":9.975059129},
{"learn":[0.2036433916],"iteration":237,"passed_time":3.111421873,"remaining_time":9.961779273},
{"learn":[0.2034899229],"iteration":238,"passed_time":3.123098724,"remaining_time":9.944259953},
{"learn":[0.2034340327],"iteration":239,"passed_time":3.133753552,"remaining_time":9.923552915},
{"learn":[0.2033321522],"iteration":240,"passed_time":3.145552619,"remaining_time":9.906532936},
{"learn":[0.2032253244],"iteration":241,"passed_time":3.157675793,"remaining_time":9.890571286},
{"learn":[0.2031359971],"iteration":242,"passed_time":3.166141392,"remaining_time":9.863247052},
{"learn":[0.2030521794],"iteration":243,"passed_time":3.177340576,"remaining_time":9.844547031},
{"learn":[0.2029649152],"iteration":244,"passed_time":3.190272507,"remaining_time":9.831247929},
{"learn":[0.202814563],"iteration":245,"passed_time":3.203562527,"remaining_time":9.819049371},
{"learn":[0.2027198808],"iteration":246,"passed_time":3.216154321,"remaining_time":9.804713377},
{"learn":[0.2026497094],"iteration":247,"passed_time":3.226832199,"remaining_time":9.784587957},
{"learn":[0.2025409531],"iteration":248,"passed_time":3.240478764,"remaining_time":9.773492177},
{"learn":[0.2024463045],"iteration":249,"passed_time":3.253042535,"remaining_time":9.759127606},
{"learn":[0.2023570679],"iteration":250,"passed_time":3.265144837,"remaining_time":9.743400332},
{"learn":[0.2022617712],"iteration":251,"passed_time":3.276990242,"remaining_time":9.726939291},
{"learn":[0.2022035439],"iteration":252,"passed_time":3.29137419,"remaining_time":9.718009961},
{"learn":[0.2021371393],"iteration":253,"passed_time":3.302935055,"remaining_time":9.700746264},
{"learn":[0.2020654424],"iteration":254,"passed_time":3.315248187,"remaining_time":9.685725096},
{"learn":[0.2019251378],"iteration":255,"passed_time":3.327047374,"remaining_time":9.669231431},
{"learn":[0.2017973805],"iteration":256,"passed_time":3.339349042,"remaining_time":9.654226996},
{"learn":[0.2016468718],"iteration":257,"passed_time":3.352717757,"remaining_time":9.642312309},
{"learn":[0.2015681709],"iteration":258,"passed_time":3.365319351,"remaining_time":9.628191656},
{"learn":[0.2014946799],"iteration":259,"passed_time":3.377505955,"remaining_time":9.612901564},
{"learn":[0.2014071471],"iteration":260,"passed_time":3.388610316,"remaining_time":9.594570971},
{"learn":[0.2013132182],"iteration":261,"passed_time":3.401366341,"remaining_time":9.580947938},
{"learn":[0.2012165759],"iteration":262,"passed_time":3.414600474,"remaining_time":9.568671291},
{"learn":[0.201123275],"iteration":263,"passed_time":3.426664813,"remaining_time":9.553126146},
{"learn":[0.2010282289],"iteration":264,"passed_time":3.438031197,"remaining_time":9.535671433},
{"learn":[0.2009571661],"iteration":265,"passed_time":3.45096401,"remaining_time":9.5225849},
{"learn":[0.2009191543],"iteration":266,"passed_time":3.463158036,"remaining_time":9.507471314},
{"learn":[0.2007669751],"iteration":267,"passed_time":3.474783695,"remaining_time":9.490827108},
{"learn":[0.2006966886],"iteration":268,"passed_time":3.484571956,"remaining_time":9.469227136},
{"learn":[0.2005663996],"iteration":269,"passed_time":3.497162858,"remaining_time":9.455292171},
{"learn":[0.2005080148],"iteration":270,"passed_time":3.509679799,"remaining_time":9.441168167},
{"learn":[0.200355023],"iteration":271,"passed_time":3.520993876,"remaining_time":9.423836551},
{"learn":[0.2002294324],"iteration":272,"passed_time":3.533168856,"remaining_time":9.408841605},
{"learn":[0.2001660843],"iteration":273,"passed_time":3.544997671,"remaining_time":9.392950033},
{"learn":[0.2000634309],"iteration":274,"passed_time":3.55796248,"remaining_time":9.380082901},
{"learn":[0.1999579664],"iteration":275,"passed_time":3.569955786,"remaining_time":9.364666628},
{"learn":[0.1998077273],"iteration":276,"passed_time":3.582611251,"remaining_time":9.351003374},
{"learn":[0.1997184045],"iteration":277,"passed_time":3.593976592,"remaining_time":9.33399676},
{"learn":[0.199675507],"iteration":278,"passed_time":3.60594021,"remaining_time":9.318576671},
{"learn":[0.1996108841],"iteration":279,"passed_time":3.617367536,"remaining_time":9.301802235},
{"learn":[0.1995431515],"iteration":280,"passed_time":3.628654512,"remaining_time":9.284706742},
{"learn":[0.1994334604],"iteration":281,"passed_time":3.640226169,"remaining_time":9.268377268},
{"learn":[0.1993653757],"iteration":282,"passed_time":3.651832972,"remaining_time":9.252170461},
{"learn":[0.1992455513],"iteration":283,"passed_time":3.662984163,"remaining_time":9.234847396},
{"learn":[0.1991290298],"iteration":284,"passed_time":3.675067909,"remaining_time":9.219907211},
{"learn":[0.1989636837],"iteration":285,"passed_time":3.686472919,"remaining_time":9.203292533},
{"learn":[0.1988894775],"iteration":286,"passed_time":3.698009431,"remaining_time":9.187040852},
{"learn":[0.1988145588],"iteration":287,"passed_time":3.709305746,"remaining_time":9.170228094},
{"learn":[0.1987163043],"iteration":288,"passed_time":3.721155995,"remaining_time":9.154816306},
{"learn":[0.1986097646],"iteration":289,"passed_time":3.734008829,"remaining_time":9.141883686},
{"learn":[0.1985274374],"iteration":290,"passed_time":3.745961455,"remaining_time":9.126758321},
{"learn":[0.1984549348],"iteration":291,"passed_time":3.756820272,"remaining_time":9.109002578},
{"learn":[0.1983664574],"iteration":292,"passed_time":3.769361877,"remaining_time":9.095354426},
{"learn":[0.198248054],"iteration":293,"passed_time":3.781934765,"remaining_time":9.081788925},
{"learn":[0.1981480827],"iteration":294,"passed_time":3.792029991,"remaining_time":9.062308963},
{"learn":[0.1980386714],"iteration":295,"passed_time":3.803316276,"remaining_time":9.045725197},
{"learn":[0.197921483],"iteration":296,"passed_time":3.815564424,"remaining_time":9.031453839},
{"learn":[0.1978517115],"iteration":297,"passed_time":3.82809325,"remaining_time":9.017857254},
{"learn":[0.1977408312],"iteration":298,"passed_time":3.838284975,"remaining_time":8.998788521},
{"learn":[0.1976607243],"iteration":299,"passed_time":3.850032056,"remaining_time":8.983408132},
{"learn":[0.1975719006],"iteration":300,"passed_time":3.862636208,"remaining_time":8.970042223},
{"learn":[0.1974974713],"iteration":301,"passed_time":3.875364962,"remaining_time":8.956969349},
{"learn":[0.197455749],"iteration":302,"passed_time":3.885244043,"remaining_time":8.937343557},
{"learn":[0.1973494288],"iteration":303,"passed_time":3.8971405,"remaining_time":8.922400619},
{"learn":[0.1972462679],"iteration":304,"passed_time":3.910188487,"remaining_time":8.910101635},
{"learn":[0.1971283667],"iteration":305,"passed_time":3.921632473,"remaining_time":8.894159923},
{"learn":[0.1970444216],"iteration":306,"passed_time":3.932785259,"remaining_time":8.877590177},
{"learn":[0.1969762128],"iteration":307,"passed_time":3.944013129,"remaining_time":8.861224303},
{"learn":[0.196894484],"iteration":308,"passed_time":3.955356033,"remaining_time":8.845148928},
{"learn":[0.1968151112],"iteration":309,"passed_time":3.967802132,"remaining_time":8.831559584},
{"learn":[0.1967490716],"iteration":310,"passed_time":3.980145514,"remaining_time":8.81775003},
{"learn":[0.1966869621],"iteration":311,"passed_time":3.991593011,"remaining_time":8.801974331},
{"learn":[0.1966237718],"iteration":312,"passed_time":4.00361059,"remaining_time":8.787477557},
{"learn":[0.1964043027],"iteration":313,"passed_time":4.014432918,"remaining_time":8.770385293},
{"learn":[0.1963381772],"iteration":314,"passed_time":4.026053783,"remaining_time":8.755069337},
{"learn":[0.1962710256],"iteration":315,"passed_time":4.038034281,"remaining_time":8.740555216},
{"learn":[0.1961103327],"iteration":316,"passed_time":4.047823574,"remaining_time":8.721335965},
{"learn":[0.1960059787],"iteration":317,"passed_time":4.060140206,"remaining_time":8.707596291},
{"learn":[0.1959107284],"iteration":318,"passed_time":4.072582554,"remaining_time":8.694133917},
{"learn":[0.1958155111],"iteration":319,"passed_time":4.083208286,"remaining_time":8.676817607},
{"learn":[0.1957794877],"iteration":320,"passed_time":4.094246991,"remaining_time":8.660416532},
{"learn":[0.1956798056],"iteration":321,"passed_time":4.106163057,"remaining_time":8.645896125},
{"learn":[0.1955979338],"iteration":322,"passed_time":4.118548996,"remaining_time":8.632376689},
{"learn":[0.1954935827],"iteration":323,"passed_time":4.128243446,"remaining_time":8.61324867},
{"learn":[0.1953863052],"iteration":324,"passed_time":4.140462025,"remaining_time":8.599421129},
{"learn":[0.1952640378],"iteration":325,"passed_time":4.153114792,"remaining_time":8.586501135},
{"learn":[0.1951638172],"iteration":326,"passed_time":4.166394321,"remaining_time":8.574872716},
{"learn":[0.1950177323],"iteration":327,"passed_time":4.179728564,"remaining_time":8.563346326},
{"learn":[0.1949974095],"iteration":328,"passed_time":4.190887007,"remaining_time":8.547371372},
{"learn":[0.1949454508],"iteration":329,"passed_time":4.202917354,"remaining_time":8.53319584},
{"learn":[0.1948428195],"iteration":330,"passed_time":4.217335635,"remaining_time":8.523859636},
{"learn":[0.1948046208],"iteration":331,"passed_time":4.229524064,"remaining_time":8.510006249},
{"learn":[0.1947430776],"iteration":332,"passed_time":4.23997714,"remaining_time":8.492686944},
{"learn":[0.1946681028],"iteration":333,"passed_time":4.251600933,"remaining_time":8.477743177},
{"learn":[0.194580005],"iteration":334,"passed_time":4.264368111,"remaining_time":8.465088937},
{"learn":[0.194452622],"iteration":335,"passed_time":4.275132787,"remaining_time":8.448476699},
{"learn":[0.1944204439],"iteration":336,"passed_time":4.28631789,"remaining_time":8.432726294},
{"learn":[0.1943504837],"iteration":337,"passed_time":4.29783706,"remaining_time":8.417657201},
{"learn":[0.1942892222],"iteration":338,"passed_time":4.309504293,"remaining_time":8.402897752},
{"learn":[0.1942058264],"iteration":339,"passed_time":4.320333272,"remaining_time":8.386529292},
{"learn":[0.1941265752],"iteration":340,"passed_time":4.332701268,"remaining_time":8.373167552},
{"learn":[0.1940663727],"iteration":341,"passed_time":4.344166306,"remaining_time":8.358074355},
{"learn":[0.193952592],"iteration":342,"passed_time":4.355653531,"remaining_time":8.34304481},
{"learn":[0.1938911222],"iteration":343,"passed_time":4.366895052,"remaining_time":8.327567308},
{"learn":[0.1938399753],"iteration":344,"passed_time":4.379499574,"remaining_time":8.314702091},
{"learn":[0.1937097417],"iteration":345,"passed_time":4.392595284,"remaining_time":8.302766809},
{"learn":[0.1936467858],"iteration":346,"passed_time":4.403415888,"remaining_time":8.286543443},
{"learn":[0.1935589303],"iteration":347,"passed_time":4.415405534,"remaining_time":8.272541402},
{"learn":[0.1934915079],"iteration":348,"passed_time":4.428700498,"remaining_time":8.260985744},
{"learn":[0.1933934349],"iteration":349,"passed_time":4.441366906,"remaining_time":8.248252825},
{"learn":[0.1933080152],"iteration":350,"passed_time":4.450379789,"remaining_time":8.22876491},
{"learn":[0.1931993435],"iteration":351,"passed_time":4.462275805,"remaining_time":8.214644096},
{"learn":[0.193158234],"iteration":352,"passed_time":4.474525759,"remaining_time":8.201184606},
{"learn":[0.1931099376],"iteration":353,"passed_time":4.486449758,"remaining_time":8.187137129},
{"learn":[0.1930288097],"iteration":354,"passed_time":4.496856796,"remaining_time":8.170345447},
{"learn":[0.1929501357],"iteration":355,"passed_time":4.510289152,"remaining_time":8.159062398},
{"learn":[0.1929067327],"iteration":356,"passed_time":4.522900214,"remaining_time":8.146288061},
{"learn":[0.1928225637],"iteration":357,"passed_time":4.535733199,"remaining_time":8.133912609},
{"learn":[0.1927532439],"iteration":358,"passed_time":4.547388907,"remaining_time":8.119432562},
{"learn":[0.1926877991],"iteration":359,"passed_time":4.558484663,"remaining_time":8.103972734},
{"learn":[0.1926193749],"iteration":360,"passed_time":4.570932226,"remaining_time":8.090929897},
{"learn":[0.1925496971],"iteration":361,"passed_time":4.582932795,"remaining_time":8.07710255},
{"learn":[0.1924761526],"iteration":362,"passed_time":4.593508547,"remaining_time":8.060784971},
{"learn":[0.1923868844],"iteration":363,"passed_time":4.606316206,"remaining_time":8.048398646},
{"learn":[0.1923117326],"iteration":364,"passed_time":4.619285037,"remaining_time":8.036290407},
{"learn":[0.1922414802],"iteration":365,"passed_time":4.631234934,"remaining_time":8.022412427},
{"learn":[0.1922119864],"iteration":366,"passed_time":4.64251471,"remaining_time":8.007389131},
{"learn":[0.1921249037],"iteration":367,"passed_time":4.654742025,"remaining_time":7.994013478},
{"learn":[0.1920870195],"iteration":368,"passed_time":4.666818932,"remaining_time":7.980386846},
{"learn":[0.1919578783],"iteration":369,"passed_time":4.679727724,"remaining_time":7.968185043},
{"learn":[0.191860598],"iteration":370,"passed_time":4.6917912,"remaining_time":7.954546266},
{"learn":[0.1917979848],"iteration":371,"passed_time":4.704509161,"remaining_time":7.942020842},
{"learn":[0.1917159986],"iteration":372,"passed_time":4.716365077,"remaining_time":7.928045318},
{"learn":[0.1916490512],"iteration":373,"passed_time":4.728660888,"remaining_time":7.914817422},
{"learn":[0.1915758831],"iteration":374,"passed_time":4.739237131,"remaining_time":7.898728552},
{"learn":[0.1915183352],"iteration":375,"passed_time":4.751357678,"remaining_time":7.885231891},
{"learn":[0.1914286064],"iteration":376,"passed_time":4.764742642,"remaining_time":7.873832005},
{"learn":[0.1913703361],"iteration":377,"passed_time":4.777356843,"remaining_time":7.861153324},
{"learn":[0.1912947389],"iteration":378,"passed_time":4.789152981,"remaining_time":7.847134569},
{"learn":[0.1911962656],"iteration":379,"passed_time":4.802211089,"remaining_time":7.835186513},
{"learn":[0.1911388738],"iteration":380,"passed_time":4.814190614,"remaining_time":7.821480289},
{"learn":[0.1910526205],"iteration":381,"passed_time":4.826530747,"remaining_time":7.808366497},
{"learn":[0.1909917442],"iteration":382,"passed_time":4.8365644,"remaining_time":7.791541083},
{"learn":[0.1908607757],"iteration":383,"passed_time":4.848674606,"remaining_time":7.77808218},
{"learn":[0.1907710825],"iteration":384,"passed_time":4.861824507,"remaining_time":7.766291096},
{"learn":[0.1907382086],"iteration":385,"passed_time":4.874896506,"remaining_time":7.754369054},
{"learn":[0.1906335583],"iteration":386,"passed_time":4.887112458,"remaining_time":7.741085108},
{"learn":[0.1905655741],"iteration":387,"passed_time":4.902932226,"remaining_time":7.733491036},
{"learn":[0.1905252262],"iteration":388,"passed_time":4.923964603,"remaining_time":7.734042089},
{"learn":[0.1904295964],"iteration":389,"passed_time":4.939588606,"remaining_time":7.726023204},
{"learn":[0.1903404391],"iteration":390,"passed_time":4.954006415,"remaining_time":7.716086718},
{"learn":[0.1902617833],"iteration":391,"passed_time":4.965827266,"remaining_time":7.702099434},
{"learn":[0.1902138041],"iteration":392,"passed_time":4.977440989,"remaining_time":7.687803258},
{"learn":[0.1901224348],"iteration":393,"passed_time":4.989739768,"remaining_time":7.674574365},
{"learn":[0.1900611999],"iteration":394,"passed_time":5.00162085,"remaining_time":7.660710416},
{"learn":[0.1899743632],"iteration":395,"passed_time":5.012209581,"remaining_time":7.644885321},
{"learn":[0.1899175827],"iteration":396,"passed_time":5.02448485,"remaining_time":7.631648274},
{"learn":[0.189727683],"iteration":397,"passed_time":5.036512519,"remaining_time":7.618041549},
{"learn":[0.1896659451],"iteration":398,"passed_time":5.047648455,"remaining_time":7.603099552},
{"learn":[0.1895926133],"iteration":399,"passed_time":5.059301756,"remaining_time":7.588952634},
{"learn":[0.1895155706],"iteration":400,"passed_time":5.071092919,"remaining_time":7.575024085},
{"learn":[0.1894429027],"iteration":401,"passed_time":5.082186849,"remaining_time":7.560068994},
{"learn":[0.1893639311],"iteration":402,"passed_time":5.092691107,"remaining_time":7.544259531},
{"learn":[0.1892869212],"iteration":403,"passed_time":5.105134157,"remaining_time":7.531336529},
{"learn":[0.1892307383],"iteration":404,"passed_time":5.117572614,"remaining_time":7.518409149},
{"learn":[0.1891637728],"iteration":405,"passed_time":5.128407811,"remaining_time":7.503138521},
{"learn":[0.1890902473],"iteration":406,"passed_time":5.139361422,"remaining_time":7.488062219},
{"learn":[0.1889929731],"iteration":407,"passed_time":5.150779881,"remaining_time":7.473680612},
{"learn":[0.1889187623],"iteration":408,"passed_time":5.163051258,"remaining_time":7.460545951},
{"learn":[0.1888294469],"iteration":409,"passed_time":5.174544732,"remaining_time":7.446296078},
{"learn":[0.1887392722],"iteration":410,"passed_time":5.187028373,"remaining_time":7.433478618},
{"learn":[0.188709402],"iteration":411,"passed_time":5.198836567,"remaining_time":7.41969879},
{"learn":[0.1885428301],"iteration":412,"passed_time":5.210540419,"remaining_time":7.405780208},
{"learn":[0.1884912131],"iteration":413,"passed_time":5.221478564,"remaining_time":7.390788498},
{"learn":[0.1884046241],"iteration":414,"passed_time":5.234314016,"remaining_time":7.378490842},
{"learn":[0.1883139373],"iteration":415,"passed_time":5.246760376,"remaining_time":7.365644374},
{"learn":[0.1883139385],"iteration":416,"passed_time":5.254799772,"remaining_time":7.346638529},
{"learn":[0.1883079153],"iteration":417,"passed_time":5.279648741,"remaining_time":7.351089874},
{"learn":[0.1882617287],"iteration":418,"passed_time":5.291736419,"remaining_time":7.337706109},
{"learn":[0.1882288734],"iteration":419,"passed_time":5.302521417,"remaining_time":7.322529575},
{"learn":[0.1881862485],"iteration":420,"passed_time":5.313550192,"remaining_time":7.307709172},
{"learn":[0.1880710007],"iteration":421,"passed_time":5.326063202,"remaining_time":7.294939646},
{"learn":[0.1880093351],"iteration":422,"passed_time":5.337226559,"remaining_time":7.280330318},
{"learn":[0.1879426846],"iteration":423,"passed_time":5.348728357,"remaining_time":7.266197014},
{"learn":[0.187892365],"iteration":424,"passed_time":5.359861785,"remaining_time":7.25157771},
{"learn":[0.1878063105],"iteration":425,"passed_time":5.373254101,"remaining_time":7.240018437},
{"learn":[0.1877459386],"iteration":426,"passed_time":5.383681992,"remaining_time":7.224472555},
{"learn":[0.1877001714],"iteration":427,"passed_time":5.396015765,"remaining_time":7.211497705},
{"learn":[0.1875968627],"iteration":428,"passed_time":5.407955703,"remaining_time":7.198001646},
{"learn":[0.1875336041],"iteration":429,"passed_time":5.419255828,"remaining_time":7.183664703},
{"learn":[0.1874527676],"iteration":430,"passed_time":5.428792637,"remaining_time":7.167013945},
{"learn":[0.1873875018],"iteration":431,"passed_time":5.440655965,"remaining_time":7.153455066},
{"learn":[0.1872582257],"iteration":432,"passed_time":5.453262494,"remaining_time":7.140877215},
{"learn":[0.1872234488],"iteration":433,"passed_time":5.464246977,"remaining_time":7.126183846},
{"learn":[0.1871337416],"iteration":434,"passed_time":5.476560791,"remaining_time":7.113234131},
{"learn":[0.1870689018],"iteration":435,"passed_time":5.488681739,"remaining_time":7.100037846},
{"learn":[0.1869748476],"iteration":436,"passed_time":5.501433351,"remaining_time":7.087658985},
{"learn":[0.1868967637],"iteration":437,"passed_time":5.515010569,"remaining_time":7.076337762},
{"learn":[0.1868269152],"iteration":438,"passed_time":5.526848963,"remaining_time":7.06278421},
{"learn":[0.1867932168],"iteration":439,"passed_time":5.540282371,"remaining_time":7.051268473},
{"learn":[0.1867662579],"iteration":440,"passed_time":5.553336176,"remaining_time":7.039262863},
{"learn":[0.1866888707],"iteration":441,"passed_time":5.565148973,"remaining_time":7.025685808},
{"learn":[0.1866161641],"iteration":442,"passed_time":5.576289182,"remaining_time":7.011271048},
{"learn":[0.1865765106],"iteration":443,"passed_time":5.589152527,"remaining_time":6.999028841},
{"learn":[0.1865279431],"iteration":444,"passed_time":5.601548899,"remaining_time":6.986201435},
{"learn":[0.1864545699],"iteration":445,"passed_time":5.614997643,"remaining_time":6.974683171},
{"learn":[0.1863602631],"iteration":446,"passed_time":5.627235791,"remaining_time":6.961658596},
{"learn":[0.1862894494],"iteration":447,"passed_time":5.639472665,"remaining_time":6.948635962},
{"learn":[0.1862593415],"iteration":448,"passed_time":5.652000509,"remaining_time":6.935973898},
{"learn":[0.1861975235],"iteration":449,"passed_time":5.664174966,"remaining_time":6.922880515},
{"learn":[0.1861350385],"iteration":450,"passed_time":5.674459318,"remaining_time":6.907490389},
{"learn":[0.1860720211],"iteration":451,"passed_time":5.685499177,"remaining_time":6.893038825},
{"learn":[0.1860322996],"iteration":452,"passed_time":5.698041062,"remaining_time":6.880416028},
{"learn":[0.1859511857],"iteration":453,"passed_time":5.711267261,"remaining_time":6.868616574},
{"learn":[0.1858821957],"iteration":454,"passed_time":5.722280952,"remaining_time":6.854160701},
{"learn":[0.185739375],"iteration":455,"passed_time":5.734411829,"remaining_time":6.841052709},
{"learn":[0.1856720535],"iteration":456,"passed_time":5.747884636,"remaining_time":6.829543451},
{"learn":[0.1855909222],"iteration":457,"passed_time":5.762475753,"remaining_time":6.819349035},
{"learn":[0.1855174223],"iteration":458,"passed_time":5.776958987,"remaining_time":6.809008305},
{"learn":[0.1854606524],"iteration":459,"passed_time":5.790017205,"remaining_time":6.796976719},
{"learn":[0.1853843243],"iteration":460,"passed_time":5.801685842,"remaining_time":6.783315984},
{"learn":[0.1852804698],"iteration":461,"passed_time":5.814274908,"remaining_time":6.770735715},
{"learn":[0.1852396773],"iteration":462,"passed_time":5.827429383,"remaining_time":6.758811185},
{"learn":[0.1851775133],"iteration":463,"passed_time":5.840341385,"remaining_time":6.746601255},
{"learn":[0.1851370968],"iteration":464,"passed_time":5.852929749,"remaining_time":6.734015948},
{"learn":[0.1850516496],"iteration":465,"passed_time":5.865019353,"remaining_time":6.720859087},
{"learn":[0.1849910639],"iteration":466,"passed_time":5.878186908,"remaining_time":6.708937092},
{"learn":[0.1849340872],"iteration":467,"passed_time":5.891480107,"remaining_time":6.697152601},
{"learn":[0.1848947292],"iteration":468,"passed_time":5.903810842,"remaining_time":6.684271977},
{"learn":[0.1848118981],"iteration":469,"passed_time":5.91472651,"remaining_time":6.669797979},
{"learn":[0.1847673819],"iteration":470,"passed_time":5.926590971,"remaining_time":6.656404722},
{"learn":[0.1847435882],"iteration":471,"passed_time":5.939101924,"remaining_time":6.643741136},
{"learn":[0.1847351433],"iteration":472,"passed_time":5.952119029,"remaining_time":6.631642132},
{"learn":[0.184709945],"iteration":473,"passed_time":5.962787589,"remaining_time":6.616933062},
{"learn":[0.1846279896],"iteration":474,"passed_time":5.974630877,"remaining_time":6.603539391},
{"learn":[0.1845420846],"iteration":475,"passed_time":5.986835976,"remaining_time":6.590550529},
{"learn":[0.1844834649],"iteration":476,"passed_time":5.99952108,"remaining_time":6.578091247},
{"learn":[0.1844057383],"iteration":477,"passed_time":6.010672411,"remaining_time":6.563956064},
{"learn":[0.1843578266],"iteration":478,"passed_time":6.022572389,"remaining_time":6.55064763},
{"learn":[0.1843063434],"iteration":479,"passed_time":6.035124996,"remaining_time":6.538052079},
{"learn":[0.1842130108],"iteration":480,"passed_time":6.048083898,"remaining_time":6.525895099},
{"learn":[0.184119814],"iteration":481,"passed_time":6.059691452,"remaining_time":6.512282515},
{"learn":[0.184043424],"iteration":482,"passed_time":6.072088484,"remaining_time":6.499523285},
{"learn":[0.1839892117],"iteration":483,"passed_time":6.084104158,"remaining_time":6.486358978},
{"learn":[0.1838792669],"iteration":484,"passed_time":6.096798328,"remaining_time":6.473919874},
{"learn":[0.1838231025],"iteration":485,"passed_time":6.108217871,"remaining_time":6.460131658},
{"learn":[0.1837417864],"iteration":486,"passed_time":6.119453635,"remaining_time":6.446159578},
{"learn":[0.1836911628],"iteration":487,"passed_time":6.131743427,"remaining_time":6.433304579},
{"learn":[0.1836141177],"iteration":488,"passed_time":6.144452863,"remaining_time":6.420890415},
{"learn":[0.1835586185],"iteration":489,"passed_time":6.157262859,"remaining_time":6.408579711},
{"learn":[0.183472615],"iteration":490,"passed_time":6.168703114,"remaining_time":6.394847016},
{"learn":[0.1833911825],"iteration":491,"passed_time":6.18110143,"remaining_time":6.382112859},
{"learn":[0.1833434729],"iteration":492,"passed_time":6.194133018,"remaining_time":6.370031319},
{"learn":[0.183262404],"iteration":493,"passed_time":6.204971756,"remaining_time":6.355699815},
{"learn":[0.1831972446],"iteration":494,"passed_time":6.215586836,"remaining_time":6.341154247},
{"learn":[0.1831335557],"iteration":495,"passed_time":6.227185423,"remaining_time":6.327623898},
{"learn":[0.1830606418],"iteration":496,"passed_time":6.239772925,"remaining_time":6.315102175},
{"learn":[0.1829215953],"iteration":497,"passed_time":6.249359974,"remaining_time":6.299555636},
{"learn":[0.1828775315],"iteration":498,"passed_time":6.261850465,"remaining_time":6.286948062},
{"learn":[0.1828154918],"iteration":499,"passed_time":6.275980927,"remaining_time":6.275980927},
{"learn":[0.1826786907],"iteration":500,"passed_time":6.289240085,"remaining_time":6.264133338},
{"learn":[0.1826105786],"iteration":501,"passed_time":6.301256521,"remaining_time":6.251047306},
{"learn":[0.1825786655],"iteration":502,"passed_time":6.314755856,"remaining_time":6.239430737},
{"learn":[0.1824968906],"iteration":503,"passed_time":6.32765203,"remaining_time":6.227213109},
{"learn":[0.1824834363],"iteration":504,"passed_time":6.340000397,"remaining_time":6.214455835},
{"learn":[0.1824329188],"iteration":505,"passed_time":6.352174544,"remaining_time":6.201530089},
{"learn":[0.1824043291],"iteration":506,"passed_time":6.365548836,"remaining_time":6.189774312},
{"learn":[0.1823459978],"iteration":507,"passed_time":6.38070465,"remaining_time":6.179737574},
{"learn":[0.1822523043],"iteration":508,"passed_time":6.395019451,"remaining_time":6.168869451},
{"learn":[0.1821887092],"iteration":509,"passed_time":6.413090092,"remaining_time":6.161596363},
{"learn":[0.1820673621],"iteration":510,"passed_time":6.428103461,"remaining_time":6.151355366},
{"learn":[0.1819936391],"iteration":511,"passed_time":6.441129492,"remaining_time":6.139201547},
{"learn":[0.1819459585],"iteration":512,"passed_time":6.455226674,"remaining_time":6.128061189},
{"learn":[0.1818727613],"iteration":513,"passed_time":6.470499988,"remaining_time":6.11802139},
{"learn":[0.1817943403],"iteration":514,"passed_time":6.485492816,"remaining_time":6.107697118},
{"learn":[0.1817719331],"iteration":515,"passed_time":6.500279015,"remaining_time":6.097160937},
{"learn":[0.1816968172],"iteration":516,"passed_time":6.517062812,"remaining_time":6.088474542},
{"learn":[0.1816425076],"iteration":517,"passed_time":6.531516589,"remaining_time":6.077588795},
{"learn":[0.1815858973],"iteration":518,"passed_time":6.542603127,"remaining_time":6.063568601},
{"learn":[0.1815341596],"iteration":519,"passed_time":6.553289068,"remaining_time":6.049189909},
{"learn":[0.181490524],"iteration":520,"passed_time":6.566380676,"remaining_time":6.037037128},
{"learn":[0.1814358591],"iteration":521,"passed_time":6.579583034,"remaining_time":6.024982165},
{"learn":[0.1813961495],"iteration":522,"passed_time":6.590959739,"remaining_time":6.011257735},
{"learn":[0.1812882126],"iteration":523,"passed_time":6.602738194,"remaining_time":5.997907214},
{"learn":[0.1812419832],"iteration":524,"passed_time":6.614956593,"remaining_time":5.984960727},
{"learn":[0.1812081248],"iteration":525,"passed_time":6.627585658,"remaining_time":5.972387076},
{"learn":[0.1811360401],"iteration":526,"passed_time":6.635922833,"remaining_time":5.955961101},
{"learn":[0.1811207282],"iteration":527,"passed_time":6.646628564,"remaining_time":5.94168311},
{"learn":[0.1810707617],"iteration":528,"passed_time":6.658522143,"remaining_time":5.928476237},
{"learn":[0.1810040094],"iteration":529,"passed_time":6.669278003,"remaining_time":5.914265399},
{"learn":[0.1809592663],"iteration":530,"passed_time":6.680681387,"remaining_time":5.900639493},
{"learn":[0.1808833463],"iteration":531,"passed_time":6.693425667,"remaining_time":5.888201527},
{"learn":[0.1808248635],"iteration":532,"passed_time":6.706083128,"remaining_time":5.875686343},
{"learn":[0.1807828176],"iteration":533,"passed_time":6.716717204,"remaining_time":5.861404901},
{"learn":[0.1807298673],"iteration":534,"passed_time":6.728603722,"remaining_time":5.848225665},
{"learn":[0.1806105692],"iteration":535,"passed_time":6.740846724,"remaining_time":5.835359851},
{"learn":[0.1805300085],"iteration":536,"passed_time":6.752570586,"remaining_time":5.822048755},
{"learn":[0.1804652999],"iteration":537,"passed_time":6.763196157,"remaining_time":5.807800418},
{"learn":[0.1804054346],"iteration":538,"passed_time":6.775327135,"remaining_time":5.794853079},
{"learn":[0.1803848358],"iteration":539,"passed_time":6.786936054,"remaining_time":5.781464046},
{"learn":[0.1802811809],"iteration":540,"passed_time":6.797045142,"remaining_time":5.766809094},
{"learn":[0.1801844673],"iteration":541,"passed_time":6.808984517,"remaining_time":5.753717544},
{"learn":[0.1800916703],"iteration":542,"passed_time":6.820051035,"remaining_time":5.739895623},
{"learn":[0.1799368574],"iteration":543,"passed_time":6.831283208,"remaining_time":5.726222689},
{"learn":[0.1798929301],"iteration":544,"passed_time":6.842388532,"remaining_time":5.712452812},
{"learn":[0.17985296],"iteration":545,"passed_time":6.854431247,"remaining_time":5.699472136},
{"learn":[0.1797908876],"iteration":546,"passed_time":6.865051422,"remaining_time":5.685316808},
{"learn":[0.1797593939],"iteration":547,"passed_time":6.876112022,"remaining_time":5.671537653},
{"learn":[0.17969494],"iteration":548,"passed_time":6.887613911,"remaining_time":5.658130917},
{"learn":[0.1796149179],"iteration":549,"passed_time":6.899561972,"remaining_time":5.645096159},
{"learn":[0.1795754982],"iteration":550,"passed_time":6.909246983,"remaining_time":5.630221226},
{"learn":[0.1795189557],"iteration":551,"passed_time":6.920912281,"remaining_time":5.616972286},
{"learn":[0.1794681948],"iteration":552,"passed_time":6.93383707,"remaining_time":5.604747143},
{"learn":[0.1793952781],"iteration":553,"passed_time":6.944925644,"remaining_time":5.591041222},
{"learn":[0.1793402799],"iteration":554,"passed_time":6.955808293,"remaining_time":5.577179622},
{"learn":[0.1792926681],"iteration":555,"passed_time":6.972893932,"remaining_time":5.568282205},
{"learn":[0.1792583289],"iteration":556,"passed_time":6.990430257,"remaining_time":5.559713831},
{"learn":[0.1792370277],"iteration":557,"passed_time":7.004213039,"remaining_time":5.548140077},
{"learn":[0.17918986],"iteration":558,"passed_time":7.019471249,"remaining_time":5.537722398},
{"learn":[0.1791523804],"iteration":559,"passed_time":7.031493311,"remaining_time":5.524744744},
{"learn":[0.1790355876],"iteration":560,"passed_time":7.04373522,"remaining_time":5.511942534},
{"learn":[0.1789929774],"iteration":561,"passed_time":7.054467239,"remaining_time":5.497965571},
{"learn":[0.1789119556],"iteration":562,"passed_time":7.065263871,"remaining_time":5.484050287},
{"learn":[0.1788778697],"iteration":563,"passed_time":7.076807123,"remaining_time":5.470723237},
{"learn":[0.1788230014],"iteration":564,"passed_time":7.088277127,"remaining_time":5.457346107},
{"learn":[0.178742486],"iteration":565,"passed_time":7.100485356,"remaining_time":5.444541774},
{"learn":[0.1786573975],"iteration":566,"passed_time":7.112047384,"remaining_time":5.431246062},
{"learn":[0.1786042563],"iteration":567,"passed_time":7.125156604,"remaining_time":5.419133192},
{"learn":[0.1785755248],"iteration":568,"passed_time":7.137304252,"remaining_time":5.406288458},
{"learn":[0.1785126381],"iteration":569,"passed_time":7.149223778,"remaining_time":5.393274078},
{"learn":[0.178471467],"iteration":570,"passed_time":7.161872783,"remaining_time":5.380811601},
{"learn":[0.1783994196],"iteration":571,"passed_time":7.173111506,"remaining_time":5.367293225},
{"learn":[0.1783239805],"iteration":572,"passed_time":7.183457482,"remaining_time":5.35311753},
{"learn":[0.1782681508],"iteration":573,"passed_time":7.194975799,"remaining_time":5.339825245},
{"learn":[0.1782025702],"iteration":574,"passed_time":7.207236896,"remaining_time":5.32708814},
{"learn":[0.1781219305],"iteration":575,"passed_time":7.21645408,"remaining_time":5.312112031},
{"learn":[0.1780645129],"iteration":576,"passed_time":7.228026269,"remaining_time":5.298882343},
{"learn":[0.1779976235],"iteration":577,"passed_time":7.240030047,"remaining_time":5.285973494},
{"learn":[0.1779163124],"iteration":578,"passed_time":7.25051251,"remaining_time":5.271961601},
{"learn":[0.1779017268],"iteration":579,"passed_time":7.261283987,"remaining_time":5.258171163},
{"learn":[0.1778317429],"iteration":580,"passed_time":7.272706238,"remaining_time":5.244860437},
{"learn":[0.1777544482],"iteration":581,"passed_time":7.284897476,"remaining_time":5.232108497},
{"learn":[0.177754435],"iteration":582,"passed_time":7.292638209,"remaining_time":5.216175186},
{"learn":[0.1777543414],"iteration":583,"passed_time":7.302730036,"remaining_time":5.201944683},
{"learn":[0.1777379776],"iteration":584,"passed_time":7.314010032,"remaining_time":5.188571219},
{"learn":[0.1776454665],"iteration":585,"passed_time":7.325289937,"remaining_time":5.175204836},
{"learn":[0.1775859012],"iteration":586,"passed_time":7.338826163,"remaining_time":5.163433058},
{"learn":[0.1775256322],"iteration":587,"passed_time":7.351825425,"remaining_time":5.151279039},
{"learn":[0.1774809475],"iteration":588,"passed_time":7.363767609,"remaining_time":5.138384528},
{"learn":[0.1774595094],"iteration":589,"passed_time":7.374630288,"remaining_time":5.124743081},
{"learn":[0.1773788265],"iteration":590,"passed_time":7.387260246,"remaining_time":5.112334079},
{"learn":[0.177374651],"iteration":591,"passed_time":7.400332295,"remaining_time":5.100229014},
{"learn":[0.1773320743],"iteration":592,"passed_time":7.412375962,"remaining_time":5.087414868},
{"learn":[0.1772409669],"iteration":593,"passed_time":7.423301911,"remaining_time":5.073839353},
{"learn":[0.1771933832],"iteration":594,"passed_time":7.43473375,"remaining_time":5.06061709},
{"learn":[0.177156006],"iteration":595,"passed_time":7.446881137,"remaining_time":5.047885871},
{"learn":[0.177099173],"iteration":596,"passed_time":7.459290677,"remaining_time":5.035333573},
{"learn":[0.1769955184],"iteration":597,"passed_time":7.471854699,"remaining_time":5.0228856},
{"learn":[0.1769828285],"iteration":598,"passed_time":7.484936667,"remaining_time":5.010783979},
{"learn":[0.1769125742],"iteration":599,"passed_time":7.496584672,"remaining_time":4.997723115},
{"learn":[0.1768803601],"iteration":600,"passed_time":7.508004596,"remaining_time":4.984515531},
{"learn":[0.1768377078],"iteration":601,"passed_time":7.51877848,"remaining_time":4.970886769},
{"learn":[0.1767906236],"iteration":602,"passed_time":7.531384116,"remaining_time":4.958473456},
{"learn":[0.1767272993],"iteration":603,"passed_time":7.543558734,"remaining_time":4.945776919},
{"learn":[0.1766468732],"iteration":604,"passed_time":7.555450016,"remaining_time":4.932897118},
{"learn":[0.1766212015],"iteration":605,"passed_time":7.566942346,"remaining_time":4.919761195},
{"learn":[0.1765496339],"iteration":606,"passed_time":7.577845978,"remaining_time":4.906249538},
{"learn":[0.1764917125],"iteration":607,"passed_time":7.590851669,"remaining_time":4.894101734},
{"learn":[0.1764061849],"iteration":608,"passed_time":7.600927608,"remaining_time":4.880070106},
{"learn":[0.1763402213],"iteration":609,"passed_time":7.612448764,"remaining_time":4.866975439},
{"learn":[0.1762665001],"iteration":610,"passed_time":7.625167678,"remaining_time":4.854648489},
{"learn":[0.1762173338],"iteration":611,"passed_time":7.637033795,"remaining_time":4.841779595},
{"learn":[0.176145732],"iteration":612,"passed_time":7.647236132,"remaining_time":4.827863594},
{"learn":[0.1760737551],"iteration":613,"passed_time":7.65923993,"remaining_time":4.815092204},
{"learn":[0.1760294715],"iteration":614,"passed_time":7.671721626,"remaining_time":4.802622481},
{"learn":[0.1759991588],"iteration":615,"passed_time":7.683335689,"remaining_time":4.789611858},
{"learn":[0.175973701],"iteration":616,"passed_time":7.694485025,"remaining_time":4.776317285},
{"learn":[0.1759502399],"iteration":617,"passed_time":7.706030253,"remaining_time":4.763274364},
{"learn":[0.1759141945],"iteration":618,"passed_time":7.719229653,"remaining_time":4.751254439},
{"learn":[0.1758658862],"iteration":619,"passed_time":7.730929412,"remaining_time":4.738311575},
{"learn":[0.1758310931],"iteration":620,"passed_time":7.742486045,"remaining_time":4.725285364},
{"learn":[0.1757566297],"iteration":621,"passed_time":7.754556462,"remaining_time":4.712576113},
{"learn":[0.1756864251],"iteration":622,"passed_time":7.767786131,"remaining_time":4.70057042},
{"learn":[0.1756612233],"iteration":623,"passed_time":7.779713802,"remaining_time":4.687776265},
{"learn":[0.1755713608],"iteration":624,"passed_time":7.791931649,"remaining_time":4.67515899},
{"learn":[0.1754991345],"iteration":625,"passed_time":7.802929733,"remaining_time":4.66181425},
{"learn":[0.1754630451],"iteration":626,"passed_time":7.815604957,"remaining_time":4.649474719},
{"learn":[0.1754106734],"iteration":627,"passed_time":7.826367728,"remaining_time":4.636001265},
{"learn":[0.1753679444],"iteration":628,"passed_time":7.840117843,"remaining_time":4.624298441},
{"learn":[0.1753172504],"iteration":629,"passed_time":7.860210484,"remaining_time":4.616314094},
{"learn":[0.1752715916],"iteration":630,"passed_time":7.875520719,"remaining_time":4.605494684},
{"learn":[0.1752148202],"iteration":631,"passed_time":7.88898492,"remaining_time":4.593586156},
{"learn":[0.1751730976],"iteration":632,"passed_time":7.902303215,"remaining_time":4.58158812},
{"learn":[0.1751274006],"iteration":633,"passed_time":7.915763253,"remaining_time":4.569667745},
{"learn":[0.1751141881],"iteration":634,"passed_time":7.928152963,"remaining_time":4.557127294},
{"learn":[0.1750691184],"iteration":635,"passed_time":7.941011415,"remaining_time":4.544855589},
{"learn":[0.1750454414],"iteration":636,"passed_time":7.952425571,"remaining_time":4.531758999},
{"learn":[0.1749509689],"iteration":637,"passed_time":7.965018469,"remaining_time":4.519336498},
{"learn":[0.1748805542],"iteration":638,"passed_time":7.978002074,"remaining_time":4.507134192},
{"learn":[0.1748441849],"iteration":639,"passed_time":7.990501803,"remaining_time":4.494657264},
{"learn":[0.1747992335],"iteration":640,"passed_time":8.00231452,"remaining_time":4.481795496},
{"learn":[0.1747510708],"iteration":641,"passed_time":8.017004442,"remaining_time":4.470541418},
{"learn":[0.1746838047],"iteration":642,"passed_time":8.031945535,"remaining_time":4.459416106},
{"learn":[0.1746402786],"iteration":643,"passed_time":8.049160419,"remaining_time":4.449535884},
{"learn":[0.1745945918],"iteration":644,"passed_time":8.075174068,"remaining_time":4.44447565},
{"learn":[0.1745645279],"iteration":645,"passed_time":8.095482284,"remaining_time":4.436224038},
{"learn":[0.174515481],"iteration":646,"passed_time":8.11228613,"remaining_time":4.42602319},
{"learn":[0.1744462934],"iteration":647,"passed_time":8.129053067,"remaining_time":4.415781913},
{"learn":[0.1744034932],"iteration":648,"passed_time":8.142954223,"remaining_time":4.40397062},
{"learn":[0.1743191734],"iteration":649,"passed_time":8.156487038,"remaining_time":4.391954559},
{"learn":[0.1742986221],"iteration":650,"passed_time":8.168137441,"remaining_time":4.37892468},
{"learn":[0.1742530841],"iteration":651,"passed_time":8.179558137,"remaining_time":4.365776429},
{"learn":[0.1742220322],"iteration":652,"passed_time":8.192907253,"remaining_time":4.353658219},
{"learn":[0.1741444578],"iteration":653,"passed_time":8.204814924,"remaining_time":4.340773645},
{"learn":[0.1740804381],"iteration":654,"passed_time":8.216076997,"remaining_time":4.327552006},
{"learn":[0.1740517388],"iteration":655,"passed_time":8.227044027,"remaining_time":4.314181624},
{"learn":[0.1740100011],"iteration":656,"passed_time":8.240078254,"remaining_time":4.301897779},
{"learn":[0.1739349202],"iteration":657,"passed_time":8.252502548,"remaining_time":4.289294637},
{"learn":[0.1738732432],"iteration":658,"passed_time":8.263628504,"remaining_time":4.276020212},
{"learn":[0.1737976181],"iteration":659,"passed_time":8.275661549,"remaining_time":4.263219586},
{"learn":[0.1737791304],"iteration":660,"passed_time":8.289522586,"remaining_time":4.251358784},
{"learn":[0.173716417],"iteration":661,"passed_time":8.302732306,"remaining_time":4.239159395},
{"learn":[0.1736710641],"iteration":662,"passed_time":8.314632485,"remaining_time":4.226291323},
{"learn":[0.1735959844],"iteration":663,"passed_time":8.325723266,"remaining_time":4.213016592},
{"learn":[0.1735512029],"iteration":664,"passed_time":8.338016739,"remaining_time":4.200354297},
{"learn":[0.1735182263],"iteration":665,"passed_time":8.350541804,"remaining_time":4.187809253},
{"learn":[0.1735004789],"iteration":666,"passed_time":8.362931275,"remaining_time":4.175196573},
{"learn":[0.1734571676],"iteration":667,"passed_time":8.372779574,"remaining_time":4.161321584},
{"learn":[0.1734401741],"iteration":668,"passed_time":8.384495672,"remaining_time":4.148382762},
{"learn":[0.1733881249],"iteration":669,"passed_time":8.39833069,"remaining_time":4.136491236},
{"learn":[0.1733480203],"iteration":670,"passed_time":8.411643428,"remaining_time":4.124337836},
{"learn":[0.1733150939],"iteration":671,"passed_time":8.422814118,"remaining_time":4.111135462},
{"learn":[0.1732604256],"iteration":672,"passed_time":8.435718015,"remaining_time":4.098781264},
{"learn":[0.1731940854],"iteration":673,"passed_time":8.447956133,"remaining_time":4.086103411},
{"learn":[0.1731635146],"iteration":674,"passed_time":8.460664375,"remaining_time":4.073653218},
{"learn":[0.1731000555],"iteration":675,"passed_time":8.47220875,"remaining_time":4.060644431},
{"learn":[0.1730852654],"iteration":676,"passed_time":8.483652776,"remaining_time":4.047592093},
{"learn":[0.1730322937],"iteration":677,"passed_time":8.495116972,"remaining_time":4.034554078},
{"learn":[0.1730058457],"iteration":678,"passed_time":8.507763139,"remaining_time":4.022079481},
{"learn":[0.1729715598],"iteration":679,"passed_time":8.519010257,"remaining_time":4.008946003},
{"learn":[0.1729304785],"iteration":680,"passed_time":8.531246148,"remaining_time":3.996281235},
{"learn":[0.1728705129],"iteration":681,"passed_time":8.543005055,"remaining_time":3.983395319},
{"learn":[0.172787044],"iteration":682,"passed_time":8.554357397,"remaining_time":3.970324004},
{"learn":[0.1727403555],"iteration":683,"passed_time":8.565465269,"remaining_time":3.957144773},
{"learn":[0.1726844066],"iteration":684,"passed_time":8.578127604,"remaining_time":3.944686416},
{"learn":[0.1726444464],"iteration":685,"passed_time":8.591035733,"remaining_time":3.932339971},
{"learn":[0.1725799926],"iteration":686,"passed_time":8.603108497,"remaining_time":3.919611295},
{"learn":[0.1725339198],"iteration":687,"passed_time":8.614203641,"remaining_time":3.906441186},
{"learn":[0.1724815461],"iteration":688,"passed_time":8.626859396,"remaining_time":3.893981527},
{"learn":[0.1724440761],"iteration":689,"passed_time":8.639824366,"remaining_time":3.881660222},
{"learn":[0.1724133156],"iteration":690,"passed_time":8.651608879,"remaining_time":3.86880918},
{"learn":[0.1723508714],"iteration":691,"passed_time":8.662187339,"remaining_time":3.855424422},
{"learn":[0.1722789949],"iteration":692,"passed_time":8.67451365,"remaining_time":3.842822064},
{"learn":[0.1722513511],"iteration":693,"passed_time":8.687761655,"remaining_time":3.830626897},
{"learn":[0.1722208894],"iteration":694,"passed_time":8.701528881,"remaining_time":3.818656559},
{"learn":[0.1722032855],"iteration":695,"passed_time":8.712878565,"remaining_time":3.80562512},
{"learn":[0.1721429294],"iteration":696,"passed_time":8.724039365,"remaining_time":3.792516395},
{"learn":[0.1720769779],"iteration":697,"passed_time":8.73650069,"remaining_time":3.779975943},
{"learn":[0.1720144498],"iteration":698,"passed_time":8.745957048,"remaining_time":3.766141733},
{"learn":[0.1719513492],"iteration":699,"passed_time":8.757589026,"remaining_time":3.75325244},
{"learn":[0.1718970521],"iteration":700,"passed_time":8.769438493,"remaining_time":3.7404595},
{"learn":[0.1718681191],"iteration":701,"passed_time":8.781341921,"remaining_time":3.727692154},
{"learn":[0.1718113311],"iteration":702,"passed_time":8.794408804,"remaining_time":3.715418798},
{"learn":[0.1717979338],"iteration":703,"passed_time":8.805673675,"remaining_time":3.702385522},
{"learn":[0.1717540614],"iteration":704,"passed_time":8.816461581,"remaining_time":3.689157683},
{"learn":[0.1717090227],"iteration":705,"passed_time":8.828041724,"remaining_time":3.676266667},
{"learn":[0.1716270081],"iteration":706,"passed_time":8.839089376,"remaining_time":3.66315868},
{"learn":[0.1716050901],"iteration":707,"passed_time":8.85248461,"remaining_time":3.651024726},
{"learn":[0.1715623786],"iteration":708,"passed_time":8.865204026,"remaining_time":3.638609833},
{"learn":[0.1715231781],"iteration":709,"passed_time":8.87683835,"remaining_time":3.625750875},
{"learn":[0.1714997498],"iteration":710,"passed_time":8.888516927,"remaining_time":3.61291335},
{"learn":[0.1714822919],"iteration":711,"passed_time":8.900192945,"remaining_time":3.600078045},
{"learn":[0.1714351666],"iteration":712,"passed_time":8.912453039,"remaining_time":3.587481097},
{"learn":[0.1713858426],"iteration":713,"passed_time":8.92484281,"remaining_time":3.574937036},
{"learn":[0.1713006583],"iteration":714,"passed_time":8.93690432,"remaining_time":3.562262561},
{"learn":[0.1712453746],"iteration":715,"passed_time":8.951313644,"remaining_time":3.550521054},
{"learn":[0.1711956972],"iteration":716,"passed_time":8.965784883,"remaining_time":3.538796544},
{"learn":[0.1711331938],"iteration":717,"passed_time":8.979945725,"remaining_time":3.526942471},
{"learn":[0.1710878797],"iteration":718,"passed_time":8.995330342,"remaining_time":3.515560259},
{"learn":[0.171043979],"iteration":719,"passed_time":9.009313362,"remaining_time":3.503621863},
{"learn":[0.1709823895],"iteration":720,"passed_time":9.024302799,"remaining_time":3.492067241},
{"learn":[0.1708980766],"iteration":721,"passed_time":9.040496493,"remaining_time":3.480966794},
{"learn":[0.1708372073],"iteration":722,"passed_time":9.05451854,"remaining_time":3.469020243},
{"learn":[0.1707719897],"iteration":723,"passed_time":9.06841781,"remaining_time":3.457021154},
{"learn":[0.1707344662],"iteration":724,"passed_time":9.080732517,"remaining_time":3.444415782},
{"learn":[0.1706743745],"iteration":725,"passed_time":9.092111408,"remaining_time":3.431458025},
{"learn":[0.1706090047],"iteration":726,"passed_time":9.105598367,"remaining_time":3.419296223},
{"learn":[0.1705489682],"iteration":727,"passed_time":9.116990789,"remaining_time":3.406348207},
{"learn":[0.1705024797],"iteration":728,"passed_time":9.127765586,"remaining_time":3.393174861},
{"learn":[0.170465029],"iteration":729,"passed_time":9.139270864,"remaining_time":3.380278265},
{"learn":[0.1704058073],"iteration":730,"passed_time":9.152043128,"remaining_time":3.367851712},
{"learn":[0.1703693625],"iteration":731,"passed_time":9.162624025,"remaining_time":3.354621911},
{"learn":[0.1703233532],"iteration":732,"passed_time":9.174746949,"remaining_time":3.341961031},
{"learn":[0.1702718609],"iteration":733,"passed_time":9.186926011,"remaining_time":3.32932196},
{"learn":[0.1702309485],"iteration":734,"passed_time":9.198124975,"remaining_time":3.316330773},
{"learn":[0.1701791365],"iteration":735,"passed_time":9.208124505,"remaining_time":3.302914225},
{"learn":[0.1701187085],"iteration":736,"passed_time":9.220205915,"remaining_time":3.290249872},
{"learn":[0.1700642064],"iteration":737,"passed_time":9.23047449,"remaining_time":3.276943518},
{"learn":[0.1700509041],"iteration":738,"passed_time":9.241655149,"remaining_time":3.263967515},
{"learn":[0.1700088534],"iteration":739,"passed_time":9.253988251,"remaining_time":3.251401277},
{"learn":[0.1699551357],"iteration":740,"passed_time":9.267123268,"remaining_time":3.23911596},
{"learn":[0.1699407138],"iteration":741,"passed_time":9.279478054,"remaining_time":3.226557059},
{"learn":[0.1698783032],"iteration":742,"passed_time":9.290531784,"remaining_time":3.213548679},
{"learn":[0.1698306632],"iteration":743,"passed_time":9.30246134,"remaining_time":3.200846913},
{"learn":[0.1697866963],"iteration":744,"passed_time":9.314575889,"remaining_time":3.188210539},
{"learn":[0.1697538419],"iteration":745,"passed_time":9.32659751,"remaining_time":3.175543924},
{"learn":[0.1697260615],"iteration":746,"passed_time":9.337010055,"remaining_time":3.162334061},
{"learn":[0.1696982646],"iteration":747,"passed_time":9.349144844,"remaining_time":3.149711899},
{"learn":[0.1696304478],"iteration":748,"passed_time":9.36155633,"remaining_time":3.137183763},
{"learn":[0.1695873555],"iteration":749,"passed_time":9.370831407,"remaining_time":3.123610469},
{"learn":[0.1695285642],"iteration":750,"passed_time":9.38139422,"remaining_time":3.11047558},
{"learn":[0.1694691028],"iteration":751,"passed_time":9.3948448,"remaining_time":3.098299881},
{"learn":[0.1694200176],"iteration":752,"passed_time":9.408836005,"remaining_time":3.086298132},
{"learn":[0.1693832188],"iteration":753,"passed_time":9.42014916,"remaining_time":3.073417365},
{"learn":[0.1693355541],"iteration":754,"passed_time":9.432845838,"remaining_time":3.060989709},
{"learn":[0.169292799],"iteration":755,"passed_time":9.444791241,"remaining_time":3.048318866},
{"learn":[0.1692206248],"iteration":756,"passed_time":9.458060349,"remaining_time":3.036074854},
{"learn":[0.1691619005],"iteration":757,"passed_time":9.469868081,"remaining_time":3.023361577},
{"learn":[0.1690867581],"iteration":758,"passed_time":9.48148018,"remaining_time":3.010588568},
{"learn":[0.1690368562],"iteration":759,"passed_time":9.493595772,"remaining_time":2.997977612},
{"learn":[0.1689809735],"iteration":760,"passed_time":9.505312251,"remaining_time":2.985242612},
{"learn":[0.1689378635],"iteration":761,"passed_time":9.515612651,"remaining_time":2.972067993},
{"learn":[0.168878661],"iteration":762,"passed_time":9.528460761,"remaining_time":2.959692268},
{"learn":[0.168859649],"iteration":763,"passed_time":9.540519503,"remaining_time":2.94707147},
{"learn":[0.1688053685],"iteration":764,"passed_time":9.551495741,"remaining_time":2.934119607},
{"learn":[0.1687036359],"iteration":765,"passed_time":9.56210372,"remaining_time":2.921060405},
{"learn":[0.168661079],"iteration":766,"passed_time":9.573838404,"remaining_time":2.908349867},
{"learn":[0.1686334496],"iteration":767,"passed_time":9.585126785,"remaining_time":2.89550705},
{"learn":[0.1685685575],"iteration":768,"passed_time":9.595366474,"remaining_time":2.882353258},
{"learn":[0.168524403],"iteration":769,"passed_time":9.607111097,"remaining_time":2.869656562},
{"learn":[0.1684736389],"iteration":770,"passed_time":9.61905624,"remaining_time":2.857021892},
{"learn":[0.168412363],"iteration":771,"passed_time":9.627649299,"remaining_time":2.843399016},
{"learn":[0.1683871729],"iteration":772,"passed_time":9.639982441,"remaining_time":2.83088747},
{"learn":[0.1683288621],"iteration":773,"passed_time":9.652809509,"remaining_time":2.818520606},
{"learn":[0.1683124005],"iteration":774,"passed_time":9.66460362,"remaining_time":2.805852664},
{"learn":[0.168249101],"iteration":775,"passed_time":9.674466954,"remaining_time":2.792629636},
{"learn":[0.1681931363],"iteration":776,"passed_time":9.68656372,"remaining_time":2.780056254},
{"learn":[0.1681597809],"iteration":777,"passed_time":9.698738488,"remaining_time":2.767506355},
{"learn":[0.1681457998],"iteration":778,"passed_time":9.709460407,"remaining_time":2.75454525},
{"learn":[0.1681344115],"iteration":779,"passed_time":9.720311582,"remaining_time":2.741626344},
{"learn":[0.1681152539],"iteration":780,"passed_time":9.732559198,"remaining_time":2.729104308},
{"learn":[0.1680728605],"iteration":781,"passed_time":9.743842184,"remaining_time":2.716314061},
{"learn":[0.1680332007],"iteration":782,"passed_time":9.755045811,"remaining_time":2.703505672},
{"learn":[0.1679987408],"iteration":783,"passed_time":9.76702974,"remaining_time":2.690916357},
{"learn":[0.1679327269],"iteration":784,"passed_time":9.780222139,"remaining_time":2.678659567},
{"learn":[0.1678630919],"iteration":785,"passed_time":9.79216345,"remaining_time":2.666059769},
{"learn":[0.1678257616],"iteration":786,"passed_time":9.802814467,"remaining_time":2.653112429},
{"learn":[0.167784186],"iteration":787,"passed_time":9.813878979,"remaining_time":2.640282162},
{"learn":[0.1677524837],"iteration":788,"passed_time":9.825990067,"remaining_time":2.627736254},
{"learn":[0.1676807459],"iteration":789,"passed_time":9.836406704,"remaining_time":2.614741023},
{"learn":[0.1676235071],"iteration":790,"passed_time":9.848524011,"remaining_time":2.602201667},
{"learn":[0.1675479993],"iteration":791,"passed_time":9.860619714,"remaining_time":2.589657703},
{"learn":[0.1674930378],"iteration":792,"passed_time":9.87118013,"remaining_time":2.576714107},
{"learn":[0.1674569913],"iteration":793,"passed_time":9.881839161,"remaining_time":2.5638021},
{"learn":[0.1673988961],"iteration":794,"passed_time":9.894490965,"remaining_time":2.55140962},
{"learn":[0.1673539134],"iteration":795,"passed_time":9.907135106,"remaining_time":2.539014525},
{"learn":[0.1673408771],"iteration":796,"passed_time":9.916749777,"remaining_time":2.525847183},
{"learn":[0.1673098223],"iteration":797,"passed_time":9.928863202,"remaining_time":2.513321262},
{"learn":[0.1672576814],"iteration":798,"passed_time":9.940465661,"remaining_time":2.500667832},
{"learn":[0.1672051104],"iteration":799,"passed_time":9.952174107,"remaining_time":2.488043527},
{"learn":[0.1671322208],"iteration":800,"passed_time":9.96376451,"remaining_time":2.475392182},
{"learn":[0.1670397869],"iteration":801,"passed_time":9.975349767,"remaining_time":2.462742212},
{"learn":[0.1670063978],"iteration":802,"passed_time":9.987092345,"remaining_time":2.450133489},
{"learn":[0.1669546518],"iteration":803,"passed_time":9.997222907,"remaining_time":2.437133943},
{"learn":[0.1669151036],"iteration":804,"passed_time":10.0102389,"remaining_time":2.424840479},
{"learn":[0.1668243512],"iteration":805,"passed_time":10.02272903,"remaining_time":2.41241865},
{"learn":[0.1667908523],"iteration":806,"passed_time":10.03628816,"remaining_time":2.400252312},
{"learn":[0.1667586671],"iteration":807,"passed_time":10.04890849,"remaining_time":2.387859444},
{"learn":[0.1667194598],"iteration":808,"passed_time":10.0606629,"remaining_time":2.375261574},
{"learn":[0.1666831557],"iteration":809,"passed_time":10.07206703,"remaining_time":2.362583625},
{"learn":[0.1666430331],"iteration":810,"passed_time":10.08462263,"remaining_time":2.35017716},
{"learn":[0.1666162084],"iteration":811,"passed_time":10.09499881,"remaining_time":2.337265733},
{"learn":[0.166585679],"iteration":812,"passed_time":10.1068084,"remaining_time":2.324690248},
{"learn":[0.1665737063],"iteration":813,"passed_time":10.11789999,"remaining_time":2.311952577},
{"learn":[0.1665292311],"iteration":814,"passed_time":10.13050652,"remaining_time":2.299562831},
{"learn":[0.1664805294],"iteration":815,"passed_time":10.14135525,"remaining_time":2.286776184},
{"learn":[0.1664407549],"iteration":816,"passed_time":10.15368451,"remaining_time":2.274325907},
{"learn":[0.1663946384],"iteration":817,"passed_time":10.16555777,"remaining_time":2.261774467},
{"learn":[0.1663442917],"iteration":818,"passed_time":10.17740112,"remaining_time":2.249218074},
{"learn":[0.1662704969],"iteration":819,"passed_time":10.18702515,"remaining_time":2.236176252},
{"learn":[0.1662497673],"iteration":820,"passed_time":10.19915384,"remaining_time":2.22368884},
{"learn":[0.1661884704],"iteration":821,"passed_time":10.21103333,"remaining_time":2.211148336},
{"learn":[0.1661321427],"iteration":822,"passed_time":10.22105418,"remaining_time":2.198209708},
{"learn":[0.166071687],"iteration":823,"passed_time":10.23244176,"remaining_time":2.185570084},
{"learn":[0.1660540707],"iteration":824,"passed_time":10.24487494,"remaining_time":2.17315529},
{"learn":[0.1660295355],"iteration":825,"passed_time":10.25489171,"remaining_time":2.160231426},
{"learn":[0.1659687891],"iteration":826,"passed_time":10.26684422,"remaining_time":2.147719528},
{"learn":[0.1659230289],"iteration":827,"passed_time":10.27959295,"remaining_time":2.135374381},
{"learn":[0.165871487],"iteration":828,"passed_time":10.29815602,"remaining_time":2.124227599},
{"learn":[0.1658383662],"iteration":829,"passed_time":10.31537107,"remaining_time":2.112786845},
{"learn":[0.1657906868],"iteration":830,"passed_time":10.33105222,"remaining_time":2.101020247},
{"learn":[0.1657335134],"iteration":831,"passed_time":10.34321254,"remaining_time":2.088533302},
{"learn":[0.1656867512],"iteration":832,"passed_time":10.35690253,"remaining_time":2.076353808},
{"learn":[0.165649742],"iteration":833,"passed_time":10.3677652,"remaining_time":2.063607941},
{"learn":[0.1655860465],"iteration":834,"passed_time":10.38086983,"remaining_time":2.051309608},
{"learn":[0.1655579428],"iteration":835,"passed_time":10.39221895,"remaining_time":2.038664961},
{"learn":[0.1655099589],"iteration":836,"passed_time":10.40499447,"remaining_time":2.026301193},
{"learn":[0.1654721968],"iteration":837,"passed_time":10.4159316,"remaining_time":2.01358105},
{"learn":[0.1654066645],"iteration":838,"passed_time":10.4285181,"remaining_time":2.001181662},
{"learn":[0.1653654666],"iteration":839,"passed_time":10.44001781,"remaining_time":1.988574821},
{"learn":[0.1653243244],"iteration":840,"passed_time":10.45224179,"remaining_time":1.976107544},
{"learn":[0.1652845501],"iteration":841,"passed_time":10.46248217,"remaining_time":1.963268625},
{"learn":[0.1652665537],"iteration":842,"passed_time":10.47539142,"remaining_time":1.950932922},
{"learn":[0.1652248515],"iteration":843,"passed_time":10.48890908,"remaining_time":1.938708314},
{"learn":[0.1651699625],"iteration":844,"passed_time":10.50129738,"remaining_time":1.926273484},
{"learn":[0.1651224385],"iteration":845,"passed_time":10.51290337,"remaining_time":1.913696358},
{"learn":[0.1650937313],"iteration":846,"passed_time":10.52594621,"remaining_time":1.901381075},
{"learn":[0.1650499313],"iteration":847,"passed_time":10.53803863,"remaining_time":1.888893717},
{"learn":[0.1650231493],"iteration":848,"passed_time":10.55099002,"remaining_time":1.876560063},
{"learn":[0.1649866743],"iteration":849,"passed_time":10.56077495,"remaining_time":1.863666168},
{"learn":[0.1649548139],"iteration":850,"passed_time":10.57235729,"remaining_time":1.851094285},
{"learn":[0.1649167576],"iteration":851,"passed_time":10.58484049,"remaining_time":1.838681212},
{"learn":[0.1648891888],"iteration":852,"passed_time":10.5964983,"remaining_time":1.826125732},
{"learn":[0.1648588109],"iteration":853,"passed_time":10.60708954,"remaining_time":1.813390016},
{"learn":[0.1648316301],"iteration":854,"passed_time":10.6184585,"remaining_time":1.800791207},
{"learn":[0.1648178572],"iteration":855,"passed_time":10.63063232,"remaining_time":1.788330671},
{"learn":[0.1647932303],"iteration":856,"passed_time":10.640938,"remaining_time":1.775559082},
{"learn":[0.1647507246],"iteration":857,"passed_time":10.65218304,"remaining_time":1.762948708},
{"learn":[0.1647324962],"iteration":858,"passed_time":10.66442661,"remaining_time":1.750505416},
{"learn":[0.1647139732],"iteration":859,"passed_time":10.67528931,"remaining_time":1.737837795},
{"learn":[0.1646979257],"iteration":860,"passed_time":10.68647595,"remaining_time":1.725226663},
{"learn":[0.164678384],"iteration":861,"passed_time":10.69751288,"remaining_time":1.712594869},
{"learn":[0.1645913719],"iteration":862,"passed_time":10.709362,"remaining_time":1.700095705},
{"learn":[0.1645603981],"iteration":863,"passed_time":10.71977607,"remaining_time":1.68737216},
{"learn":[0.1645029043],"iteration":864,"passed_time":10.73167187,"remaining_time":1.674885205},
{"learn":[0.1644537721],"iteration":865,"passed_time":10.743049,"remaining_time":1.66231936},
{"learn":[0.1644063425],"iteration":866,"passed_time":10.75451811,"remaining_time":1.649770367},
{"learn":[0.1643536699],"iteration":867,"passed_time":10.76630515,"remaining_time":1.637272211},
{"learn":[0.1642883105],"iteration":868,"passed_time":10.77839098,"remaining_time":1.624820735},
{"learn":[0.1642232953],"iteration":869,"passed_time":10.78976619,"remaining_time":1.612263913},
{"learn":[0.1641891328],"iteration":870,"passed_time":10.80125515,"remaining_time":1.599726653},
{"learn":[0.164139147],"iteration":871,"passed_time":10.81299334,"remaining_time":1.587228381},
{"learn":[0.1640628408],"iteration":872,"passed_time":10.82551137,"remaining_time":1.574845297},
{"learn":[0.1640212972],"iteration":873,"passed_time":10.83634093,"remaining_time":1.562218486},
{"learn":[0.1639758803],"iteration":874,"passed_time":10.8476365,"remaining_time":1.549662357},
{"learn":[0.1639195533],"iteration":875,"passed_time":10.85980941,"remaining_time":1.537233296},
{"learn":[0.1638998342],"iteration":876,"passed_time":10.87232892,"remaining_time":1.524853429},
{"learn":[0.1638346536],"iteration":877,"passed_time":10.8822552,"remaining_time":1.512112909},
{"learn":[0.1637549442],"iteration":878,"passed_time":10.89466745,"remaining_time":1.499721003},
{"learn":[0.1636964874],"iteration":879,"passed_time":10.90621529,"remaining_time":1.487211176},
{"learn":[0.1636628239],"iteration":880,"passed_time":10.91918569,"remaining_time":1.474895684},
{"learn":[0.1636031009],"iteration":881,"passed_time":10.93016246,"remaining_time":1.462311985},
{"learn":[0.1635932131],"iteration":882,"passed_time":10.9416241,"remaining_time":1.449796172},
{"learn":[0.1635443413],"iteration":883,"passed_time":10.953524,"remaining_time":1.437340254},
{"learn":[0.1635082599],"iteration":884,"passed_time":10.9661507,"remaining_time":1.424980034},
{"learn":[0.1634663322],"iteration":885,"passed_time":10.97866764,"remaining_time":1.412605091},
{"learn":[0.163407622],"iteration":886,"passed_time":10.99077525,"remaining_time":1.400177681},
{"learn":[0.1633767866],"iteration":887,"passed_time":11.00280839,"remaining_time":1.387741599},
{"learn":[0.1633296152],"iteration":888,"passed_time":11.01401592,"remaining_time":1.375203338},
{"learn":[0.1632868202],"iteration":889,"passed_time":11.025727,"remaining_time":1.362730303},
{"learn":[0.1631944105],"iteration":890,"passed_time":11.03757277,"remaining_time":1.350275457},
{"learn":[0.1631531461],"iteration":891,"passed_time":11.04912128,"remaining_time":1.337785985},
{"learn":[0.1631204679],"iteration":892,"passed_time":11.05911879,"remaining_time":1.325112777},
{"learn":[0.1630675438],"iteration":893,"passed_time":11.07107335,"remaining_time":1.3126776},
{"learn":[0.1630219905],"iteration":894,"passed_time":11.08244609,"remaining_time":1.30017524},
{"learn":[0.1630042037],"iteration":895,"passed_time":11.09427508,"remaining_time":1.287728357},
{"learn":[0.1629715843],"iteration":896,"passed_time":11.10500144,"remaining_time":1.275156241},
{"learn":[0.1629716007],"iteration":897,"passed_time":11.11363738,"remaining_time":1.262350793},
{"learn":[0.1629667726],"iteration":898,"passed_time":11.12397309,"remaining_time":1.249745586},
{"learn":[0.1629487261],"iteration":899,"passed_time":11.13515259,"remaining_time":1.237239176},
{"learn":[0.1629105768],"iteration":900,"passed_time":11.14683058,"remaining_time":1.224790486},
{"learn":[0.1628676187],"iteration":901,"passed_time":11.15714102,"remaining_time":1.212194922},
{"learn":[0.1628223803],"iteration":902,"passed_time":11.16803274,"remaining_time":1.199666861},
{"learn":[0.1627699795],"iteration":903,"passed_time":11.17989538,"remaining_time":1.187245527},
{"learn":[0.1627286976],"iteration":904,"passed_time":11.19177397,"remaining_time":1.174827102},
{"learn":[0.1626705416],"iteration":905,"passed_time":11.20190939,"remaining_time":1.16222901},
{"learn":[0.162651906],"iteration":906,"passed_time":11.21428484,"remaining_time":1.149866031},
{"learn":[0.1626491166],"iteration":907,"passed_time":11.22620567,"remaining_time":1.137456962},
{"learn":[0.1626241753],"iteration":908,"passed_time":11.23630858,"remaining_time":1.124866976},
{"learn":[0.1626205144],"iteration":909,"passed_time":11.24732283,"remaining_time":1.112372588},
{"learn":[0.1625560612],"iteration":910,"passed_time":11.25961541,"remaining_time":1.100006336},
{"learn":[0.1625148503],"iteration":911,"passed_time":11.27082515,"remaining_time":1.08753576},
{"learn":[0.1624655332],"iteration":912,"passed_time":11.28082396,"remaining_time":1.074952557},
{"learn":[0.1624557406],"iteration":913,"passed_time":11.29246283,"remaining_time":1.062529325},
{"learn":[0.1624007329],"iteration":914,"passed_time":11.30476669,"remaining_time":1.050169583},
{"learn":[0.1623283975],"iteration":915,"passed_time":11.31572821,"remaining_time":1.037686866},
{"learn":[0.1622950651],"iteration":916,"passed_time":11.32728146,"remaining_time":1.025261026},
{"learn":[0.1622816074],"iteration":917,"passed_time":11.34054247,"remaining_time":1.012989633},
{"learn":[0.1622416744],"iteration":918,"passed_time":11.35401332,"remaining_time":1.00073458},
{"learn":[0.162183598],"iteration":919,"passed_time":11.3644423,"remaining_time":0.9882123736},
{"learn":[0.162183095],"iteration":920,"passed_time":11.37323866,"remaining_time":0.9755546736},
{"learn":[0.1621471444],"iteration":921,"passed_time":11.38563332,"remaining_time":0.9632097601},
{"learn":[0.1621132583],"iteration":922,"passed_time":11.39672707,"remaining_time":0.9507562126},
{"learn":[0.1620672651],"iteration":923,"passed_time":11.40826805,"remaining_time":0.9383423941},
{"learn":[0.1620211116],"iteration":924,"passed_time":11.42028481,"remaining_time":0.9259690387},
{"learn":[0.1620210845],"iteration":925,"passed_time":11.42873516,"remaining_time":0.9133114494},
{"learn":[0.1619772979],"iteration":926,"passed_time":11.44077803,"remaining_time":0.9009458426},
{"learn":[0.1619338487],"iteration":927,"passed_time":11.45205961,"remaining_time":0.8885218662},
{"learn":[0.1619007368],"iteration":928,"passed_time":11.46435487,"remaining_time":0.8761778209},
{"learn":[0.1618410458],"iteration":929,"passed_time":11.47534549,"remaining_time":0.863735682},
{"learn":[0.1617830167],"iteration":930,"passed_time":11.48604633,"remaining_time":0.8512751849},
{"learn":[0.161757044],"iteration":931,"passed_time":11.49790247,"remaining_time":0.8389027554},
{"learn":[0.1617130469],"iteration":932,"passed_time":11.50886876,"remaining_time":0.8264675316},
{"learn":[0.1616845433],"iteration":933,"passed_time":11.52041,"remaining_time":0.8140760811},
{"learn":[0.161642485],"iteration":934,"passed_time":11.53278297,"remaining_time":0.8017442705},
{"learn":[0.161596792],"iteration":935,"passed_time":11.5449573,"remaining_time":0.7893987901},
{"learn":[0.16154855],"iteration":936,"passed_time":11.55765863,"remaining_time":0.7770891072},
{"learn":[0.1615092544],"iteration":937,"passed_time":11.57052687,"remaining_time":0.7647896223},
{"learn":[0.1614560582],"iteration":938,"passed_time":11.58257692,"remaining_time":0.7524357746},
{"learn":[0.1614143493],"iteration":939,"passed_time":11.59559794,"remaining_time":0.7401445493},
{"learn":[0.161362318],"iteration":940,"passed_time":11.6054107,"remaining_time":0.7276506179},
{"learn":[0.161320667],"iteration":941,"passed_time":11.6165729,"remaining_time":0.715245465},
{"learn":[0.1612854338],"iteration":942,"passed_time":11.62844416,"remaining_time":0.7028858081},
{"learn":[0.161272963],"iteration":943,"passed_time":11.64039726,"remaining_time":0.6905320406},
{"learn":[0.1611936525],"iteration":944,"passed_time":11.65068186,"remaining_time":0.6780820129},
{"learn":[0.161162528],"iteration":945,"passed_time":11.66245805,"remaining_time":0.6657217066},
{"learn":[0.1611217856],"iteration":946,"passed_time":11.67547905,"remaining_time":0.6534323018},
{"learn":[0.1611061479],"iteration":947,"passed_time":11.68682539,"remaining_time":0.6410494938},
{"learn":[0.1610615125],"iteration":948,"passed_time":11.69782732,"remaining_time":0.6286503619},
{"learn":[0.1610307636],"iteration":949,"passed_time":11.70988184,"remaining_time":0.6163095706},
{"learn":[0.1610019844],"iteration":950,"passed_time":11.72213985,"remaining_time":0.603979866},
{"learn":[0.1609648659],"iteration":951,"passed_time":11.73282518,"remaining_time":0.5915710174},
{"learn":[0.1609062735],"iteration":952,"passed_time":11.74464888,"remaining_time":0.5792219279},
{"learn":[0.1608546907],"iteration":953,"passed_time":11.75681437,"remaining_time":0.5668904203},
{"learn":[0.1608078421],"iteration":954,"passed_time":11.76932012,"remaining_time":0.5545752935},
{"learn":[0.160791695],"iteration":955,"passed_time":11.77975648,"remaining_time":0.5421645243},
{"learn":[0.1607904479],"iteration":956,"passed_time":11.78897349,"remaining_time":0.5297030929},
{"learn":[0.1607268548],"iteration":957,"passed_time":11.80118749,"remaining_time":0.5173798274},
{"learn":[0.160678493],"iteration":958,"passed_time":11.81195404,"remaining_time":0.504994907},
{"learn":[0.1606688345],"iteration":959,"passed_time":11.82319485,"remaining_time":0.4926331188},
{"learn":[0.1606451298],"iteration":960,"passed_time":11.83574608,"remaining_time":0.4803268439},
{"learn":[0.1606243238],"iteration":961,"passed_time":11.84630101,"remaining_time":0.467941204},
{"learn":[0.1605808079],"iteration":962,"passed_time":11.85788105,"remaining_time":0.4555987526},
{"learn":[0.1605391149],"iteration":963,"passed_time":11.87056658,"remaining_time":0.443299167},
{"learn":[0.1605036063],"iteration":964,"passed_time":11.88451552,"remaining_time":0.4310446044},
{"learn":[0.1604556014],"iteration":965,"passed_time":11.8995333,"remaining_time":0.4188241535},
{"learn":[0.1603824509],"iteration":966,"passed_time":11.91537339,"remaining_time":0.4066259792},
{"learn":[0.1603262723],"iteration":967,"passed_time":11.93088335,"remaining_time":0.394409367},
{"learn":[0.1603012191],"iteration":968,"passed_time":11.94391905,"remaining_time":0.3821068015},
{"learn":[0.1602779463],"iteration":969,"passed_time":11.95781266,"remaining_time":0.3698292574},
{"learn":[0.1601843094],"iteration":970,"passed_time":11.97105676,"remaining_time":0.3575289866},
{"learn":[0.1600840949],"iteration":971,"passed_time":11.98362664,"remaining_time":0.3452073517},
{"learn":[0.1600268761],"iteration":972,"passed_time":11.99574445,"remaining_time":0.3328726619},
{"learn":[0.1599872315],"iteration":973,"passed_time":12.00527268,"remaining_time":0.3204692912},
{"learn":[0.1599572716],"iteration":974,"passed_time":12.01727716,"remaining_time":0.3081353118},
{"learn":[0.159908706],"iteration":975,"passed_time":12.02992302,"remaining_time":0.2958177791},
{"learn":[0.1598887946],"iteration":976,"passed_time":12.04090768,"remaining_time":0.2834604674},
{"learn":[0.1598467244],"iteration":977,"passed_time":12.05134984,"remaining_time":0.2710937592},
{"learn":[0.1598018789],"iteration":978,"passed_time":12.06334194,"remaining_time":0.2587642295},
{"learn":[0.1597501036],"iteration":979,"passed_time":12.07551706,"remaining_time":0.2464391236},
{"learn":[0.1596576269],"iteration":980,"passed_time":12.08723152,"remaining_time":0.2341054015},
{"learn":[0.1596390691],"iteration":981,"passed_time":12.09837576,"remaining_time":0.2217624885},
{"learn":[0.1596074983],"iteration":982,"passed_time":12.11112304,"remaining_time":0.2094497372},
{"learn":[0.1595454747],"iteration":983,"passed_time":12.12433838,"remaining_time":0.1971437134},
{"learn":[0.1594938162],"iteration":984,"passed_time":12.13486555,"remaining_time":0.1847949069},
{"learn":[0.1594551838],"iteration":985,"passed_time":12.14703711,"remaining_time":0.1724731436},
{"learn":[0.1594335534],"iteration":986,"passed_time":12.15862361,"remaining_time":0.1601439787},
{"learn":[0.1593988478],"iteration":987,"passed_time":12.17067682,"remaining_time":0.1478219856},
{"learn":[0.1593713611],"iteration":988,"passed_time":12.18165396,"remaining_time":0.1354885678},
{"learn":[0.1593386556],"iteration":989,"passed_time":12.19394563,"remaining_time":0.123171168},
{"learn":[0.1592906909],"iteration":990,"passed_time":12.20559322,"remaining_time":0.1108479707},
{"learn":[0.159269943],"iteration":991,"passed_time":12.21681773,"remaining_time":0.09852272364},
{"learn":[0.1592113285],"iteration":992,"passed_time":12.22825147,"remaining_time":0.08620116845},
{"learn":[0.1592024826],"iteration":993,"passed_time":12.24019644,"remaining_time":0.07388448555},
{"learn":[0.1591571182],"iteration":994,"passed_time":12.25175688,"remaining_time":0.0615666175},
{"learn":[0.1591532941],"iteration":995,"passed_time":12.26178379,"remaining_time":0.04924411159},
{"learn":[0.1591029318],"iteration":996,"passed_time":12.27248652,"remaining_time":0.03692824428},
{"learn":[0.1590635593],"iteration":997,"passed_time":12.28434859,"remaining_time":0.02461793305},
{"learn":[0.1590336049],"iteration":998,"passed_time":12.29474775,"remaining_time":0.0123070548},
{"learn":[0.1589804688],"iteration":999,"passed_time":12.30774092,"remaining_time":0}
]}