{
  "avg_ot": 0.3,
  "list_ot": [0.31, 0.29, 0.31],
  "avg_tp": 1873.33,
  "list_tp": [1863, 1862, 1895],
  "avg_tn": 14740.0,
  "list_tn": [14846, 14520, 14854],
  "avg_fp": 3619.33,
  "list_fp": [3535, 3833, 3490],
  "avg_fn": 451.33,
  "list_fn": [440, 469, 445],
  "avg_acc": 80.32,
  "list_acc": [80.78, 79.2, 80.98],
  "avg_sen": 80.59,
  "list_sen": [80.89, 79.88, 80.98],
  "avg_spec": 80.29,
  "list_spec": [80.77, 79.12, 80.97],
  "avg_f1": 47.95,
  "list_f1": [48.38, 46.4, 49.06],
  "avg_auc": 88.31,
  "list_auc": [88.51, 87.82, 88.61]
}
