{
  "avg_ot": 0.5,
  "list_ot": [0.5, 0.49, 0.5],
  "avg_tp": 1877.0,
  "list_tp": [1830, 1898, 1903],
  "avg_tn": 14943.33,
  "list_tn": [14945, 14952, 14933],
  "avg_fp": 3392.67,
  "list_fp": [3453, 3348, 3377],
  "avg_fn": 471.0,
  "list_fn": [456, 486, 471],
  "avg_acc": 81.32,
  "list_acc": [81.1, 81.46, 81.4],
  "avg_sen": 79.94,
  "list_sen": [80.05, 79.61, 80.16],
  "avg_spec": 81.5,
  "list_spec": [81.23, 81.7, 81.56],
  "avg_f1": 49.28,
  "list_f1": [48.36, 49.75, 49.73],
  "avg_auc": 88.62,
  "list_auc": [88.57, 88.34, 88.94]
}
