{
  "avg_ot": 0.52,
  "list_ot": [0.52, 0.52, 0.52],
  "avg_tp": 1293.67,
  "list_tp": [1256, 1337, 1288],
  "avg_tn": 12551.67,
  "list_tn": [12547, 12510, 12598],
  "avg_fp": 2713.33,
  "list_fp": [2726, 2742, 2672],
  "avg_fn": 292.33,
  "list_fn": [322, 262, 293],
  "avg_acc": 82.16,
  "list_acc": [81.91, 82.17, 82.4],
  "avg_precision": 32.28,
  "list_precision": [31.54, 32.78, 32.53],
  "avg_recall": 81.56,
  "list_recall": [79.59, 83.61, 81.47],
  "avg_sen": 81.56,
  "list_sen": [79.59, 83.61, 81.47],
  "avg_spec": 82.23,
  "list_spec": [82.15, 82.02, 82.5],
  "avg_f1": 46.25,
  "list_f1": [45.18, 47.09, 46.49],
  "avg_auc": 89.73,
  "list_auc": [89.15, 90.32, 89.72]
}
